Workbook

Sheet README
A1: 1 ISKO STORES FY2027-28 - purchase, receipt, QC, RM and consumable stock
A2: PROTOTYPE - sample / masked data - layout of the target design, not the live ERP
A4: Daily routine
A5: Morning | B5: Refresh All (X_Product, X_Machine, X_People). Check Lot Balance status = OK.
A6: Through the day | B6: Type in the Entry sheets only. Post rows that read READY (macro button, or Copy > Paste Values into the Register).
A7: After posting | B7: Refresh All so Lot Balance / Consumable Balance include the new rows. Enter the posted totals in Posting Log.
A8: End of day | B8: Save, back up (dated copy), Control Totals checked.
A9: Never | B9: Edit or delete a register row - post a reversal row instead.
A12: Cell colours
A13: Cream | B13: you type or pick here
A14: Mint | B14: calculated / snapshot - posted as value
A15: Light grey | B15: lookup shown for information
A16: Coral | B16: hard stop - row cannot be posted
A17: Amber | B17: warning - post only with an authorised reason
A18: Teal | B18: totals
A19: Blue | B19: column headers

Sheet PO Entry
A1: PO ENTRY PAD - one PO at a time
A2: Fill the header, then the lines. Post when every line reads READY. No requisition is needed.
A3: PO No | B3: ="PO/27-28/"&TEXT(COUNTA('PO Header Register'!$A$5:$A$400)+1,"000") | C3: Supplier | D3: SUP-0007 | E3: Name | F3: =IFERROR(INDEX('M_Supplier'!$B$5:$B$50,MATCH(D3,'M_Supplier'!$A$5:$A$50,0)),"") | G3: Pay days | H3: =IFERROR(INDEX('M_Supplier'!$E$5:$E$50,MATCH(D3,'M_Supplier'!$A$5:$A$50,0)),"") | I3: Approved by | J3: PER-018
A4: PO Date | B4: 46492 | C4: Delivery by | D4: 46502 | E4: Location | F4: ISKO Factory
A6: Line | B6: PO Line ID | C6: Item ID | D6: Grade | E6: Thk mm | F6: L mm | G6: W mm | H6: Ordered kg | I6: Unit | J6: Rate Rs | K6: Line Value Rs | L6: Due Date | M6: Ready / issues
A7: 1 | B7: =IF(C7="","",$B$3&"-"&TEXT(A7,"00")) | C7: GPSP-1.6 | D7: =IF(C7="","",IFERROR(INDEX('M_Material'!$C$5:$C$50,MATCH(C7,'M_Material'!$A$5:$A$50,0)),"?")) | E7: =IF(C7="","",IFERROR(INDEX('M_Material'!$D$5:$D$50,MATCH(C7,'M_Material'!$A$5:$A$50,0)),"")) | F7: 2500 | G7: 1250 | H7: 2000 | I7: =IF(C7="","","KGS") | J7: 74.5 | K7: =IF(H7="","",ROUND(H7*J7,2)) | L7: 46502 | M7: =IF(C7="","",IF(D7="?","ITEM NOT IN MASTER",IF(N(H7)<=0,"QTY REQUIRED",IF(N(J7)<=0,"RATE REQUIRED",IF(L7<$B$4,"WARN: DUE BEFORE PO DATE","READY")))))
A8: 2 | B8: =IF(C8="","",$B$3&"-"&TEXT(A8,"00")) | C8: HRCA-2.0 | D8: =IF(C8="","",IFERROR(INDEX('M_Material'!$C$5:$C$50,MATCH(C8,'M_Material'!$A$5:$A$50,0)),"?")) | E8: =IF(C8="","",IFERROR(INDEX('M_Material'!$D$5:$D$50,MATCH(C8,'M_Material'!$A$5:$A$50,0)),"")) | F8: 2500 | G8: 1250 | H8: 800 | I8: =IF(C8="","","KGS") | K8: =IF(H8="","",ROUND(H8*J8,2)) | L8: 46502 | M8: =IF(C8="","",IF(D8="?","ITEM NOT IN MASTER",IF(N(H8)<=0,"QTY REQUIRED",IF(N(J8)<=0,"RATE REQUIRED",IF(L8<$B$4,"WARN: DUE BEFORE PO DATE","READY")))))
A9: 3 | B9: =IF(C9="","",$B$3&"-"&TEXT(A9,"00")) | C9: GPSP-2.5 | D9: =IF(C9="","",IFERROR(INDEX('M_Material'!$C$5:$C$50,MATCH(C9,'M_Material'!$A$5:$A$50,0)),"?")) | E9: =IF(C9="","",IFERROR(INDEX('M_Material'!$D$5:$D$50,MATCH(C9,'M_Material'!$A$5:$A$50,0)),"")) | F9: 2500 | G9: 1250 | H9: 500 | I9: =IF(C9="","","KGS") | J9: 75 | K9: =IF(H9="","",ROUND(H9*J9,2)) | L9: 46502 | M9: =IF(C9="","",IF(D9="?","ITEM NOT IN MASTER",IF(N(H9)<=0,"QTY REQUIRED",IF(N(J9)<=0,"RATE REQUIRED",IF(L9<$B$4,"WARN: DUE BEFORE PO DATE","READY")))))
A10: 4 | B10: =IF(C10="","",$B$3&"-"&TEXT(A10,"00")) | C10: CRCA-1.0 | D10: =IF(C10="","",IFERROR(INDEX('M_Material'!$C$5:$C$50,MATCH(C10,'M_Material'!$A$5:$A$50,0)),"?")) | E10: =IF(C10="","",IFERROR(INDEX('M_Material'!$D$5:$D$50,MATCH(C10,'M_Material'!$A$5:$A$50,0)),"")) | F10: 2500 | G10: 1250 | H10: 1000 | I10: =IF(C10="","","KGS") | J10: 68.2 | K10: =IF(H10="","",ROUND(H10*J10,2)) | L10: 46478 | M10: =IF(C10="","",IF(D10="?","ITEM NOT IN MASTER",IF(N(H10)<=0,"QTY REQUIRED",IF(N(J10)<=0,"RATE REQUIRED",IF(L10<$B$4,"WARN: DUE BEFORE PO DATE","READY")))))

Sheet GRN Entry
A1: GRN ENTRY PAD
A2: One row per lot received. Lot ID fills itself. The lot cannot be issued until Lot QC records ACCEPTED.
A4: Lot ID | B4: GRN Date | C4: Supplier ID | D4: Supplier Inv No | E4: PO Line ID | F4: Material ID | G4: Grade Code | H4: Thk mm | I4: L mm | J4: W mm | K4: Form | L4: Sheets | M4: Received kg | N4: Theo kg | O4: Theo Var % | P4: Bill Rate Rs | Q4: PO Rate Rs | R4: PO Pending kg | S4: Excess kg | T4: Ready / issues
A5: =IF(C5="","",G5&"-"&'Settings'!$B$6&"-"&TEXT(COUNTIF('GRN Register'!$H$5:$H$400,G5)+COUNTIF(G$4:G4,G5)+1,"0000")) | B5: 46492 | C5: SUP-0007 | D5: INV/3419 | E5: PO/27-28/001-01 | F5: =IF(E5="","",IFERROR(INDEX('PO Line Register'!$C$5:$C$400,MATCH(E5,'PO Line Register'!$A$5:$A$400,0)),"")) | G5: =IF(F5="","",INDEX('M_Material'!$B$5:$B$50,MATCH(F5,'M_Material'!$A$5:$A$50,0))) | H5: =IF(F5="","",INDEX('M_Material'!$D$5:$D$50,MATCH(F5,'M_Material'!$A$5:$A$50,0))) | I5: 2500 | J5: 1250 | K5: SHEET | L5: 6 | M5: 245 | N5: =IF(OR(L5="",H5=""),"",ROUND(L5*I5*J5*H5*'Settings'!$B$9,3)) | O5: =IF(N5="","",M5/N5-1) | P5: 74.5 | Q5: =IF(E5="","",IFERROR(INDEX('PO Line Register'!$J$5:$J$400,MATCH(E5,'PO Line Register'!$A$5:$A$400,0)),"")) | R5: =IF(E5="","",IFERROR(INDEX('PO Status'!$F$5:$F$100,MATCH(E5,'PO Status'!$A$5:$A$100,0)),0)-SUMIFS(M$4:M4,E$4:E4,E5)) | S5: =IF(R5="","",MAX(0,M5-R5)) | T5: =IF(C5="","",IF(F5="","NO OPEN PO LINE",IF(N(M5)<=0,"RECEIVED KG REQUIRED",IF(D5="","INVOICE NO REQUIRED",IF(S5>0,"WARN: EXCESS "&TEXT(S5,"0.0")&" kg - decide in Lot QC",IF(ABS(O5)>'Settings'!$B$10,"WARN: THEO VAR "&TEXT(O5,"+0.0%"),"READY"))))))
A6: =IF(C6="","",G6&"-"&'Settings'!$B$6&"-"&TEXT(COUNTIF('GRN Register'!$H$5:$H$400,G6)+COUNTIF(G$4:G5,G6)+1,"0000")) | B6: 46492 | C6: SUP-0007 | D6: INV/3419 | E6: PO/27-28/001-02 | F6: =IF(E6="","",IFERROR(INDEX('PO Line Register'!$C$5:$C$400,MATCH(E6,'PO Line Register'!$A$5:$A$400,0)),"")) | G6: =IF(F6="","",INDEX('M_Material'!$B$5:$B$50,MATCH(F6,'M_Material'!$A$5:$A$50,0))) | H6: =IF(F6="","",INDEX('M_Material'!$D$5:$D$50,MATCH(F6,'M_Material'!$A$5:$A$50,0))) | I6: 2500 | J6: 1250 | K6: SHEET | L6: 20 | M6: 590 | N6: =IF(OR(L6="",H6=""),"",ROUND(L6*I6*J6*H6*'Settings'!$B$9,3)) | O6: =IF(N6="","",M6/N6-1) | P6: 74.5 | Q6: =IF(E6="","",IFERROR(INDEX('PO Line Register'!$J$5:$J$400,MATCH(E6,'PO Line Register'!$A$5:$A$400,0)),"")) | R6: =IF(E6="","",IFERROR(INDEX('PO Status'!$F$5:$F$100,MATCH(E6,'PO Status'!$A$5:$A$100,0)),0)-SUMIFS(M$4:M5,E$4:E5,E6)) | S6: =IF(R6="","",MAX(0,M6-R6)) | T6: =IF(C6="","",IF(F6="","NO OPEN PO LINE",IF(N(M6)<=0,"RECEIVED KG REQUIRED",IF(D6="","INVOICE NO REQUIRED",IF(S6>0,"WARN: EXCESS "&TEXT(S6,"0.0")&" kg - decide in Lot QC",IF(ABS(O6)>'Settings'!$B$10,"WARN: THEO VAR "&TEXT(O6,"+0.0%"),"READY"))))))
A7: =IF(C7="","",G7&"-"&'Settings'!$B$6&"-"&TEXT(COUNTIF('GRN Register'!$H$5:$H$400,G7)+COUNTIF(G$4:G6,G7)+1,"0000")) | B7: 46492 | C7: SUP-0012 | D7: B-77311 | E7: PO/27-28/009-01 | F7: =IF(E7="","",IFERROR(INDEX('PO Line Register'!$C$5:$C$400,MATCH(E7,'PO Line Register'!$A$5:$A$400,0)),"")) | G7: =IF(F7="","",INDEX('M_Material'!$B$5:$B$50,MATCH(F7,'M_Material'!$A$5:$A$50,0))) | H7: =IF(F7="","",INDEX('M_Material'!$D$5:$D$50,MATCH(F7,'M_Material'!$A$5:$A$50,0))) | I7: 2500 | J7: 1250 | K7: SHEET | L7: 10 | M7: 245.4 | N7: =IF(OR(L7="",H7=""),"",ROUND(L7*I7*J7*H7*'Settings'!$B$9,3)) | O7: =IF(N7="","",M7/N7-1) | P7: 68.2 | Q7: =IF(E7="","",IFERROR(INDEX('PO Line Register'!$J$5:$J$400,MATCH(E7,'PO Line Register'!$A$5:$A$400,0)),"")) | R7: =IF(E7="","",IFERROR(INDEX('PO Status'!$F$5:$F$100,MATCH(E7,'PO Status'!$A$5:$A$100,0)),0)-SUMIFS(M$4:M6,E$4:E6,E7)) | S7: =IF(R7="","",MAX(0,M7-R7)) | T7: =IF(C7="","",IF(F7="","NO OPEN PO LINE",IF(N(M7)<=0,"RECEIVED KG REQUIRED",IF(D7="","INVOICE NO REQUIRED",IF(S7>0,"WARN: EXCESS "&TEXT(S7,"0.0")&" kg - decide in Lot QC",IF(ABS(O7)>'Settings'!$B$10,"WARN: THEO VAR "&TEXT(O7,"+0.0%"),"READY"))))))
A8: =IF(C8="","",G8&"-"&'Settings'!$B$6&"-"&TEXT(COUNTIF('GRN Register'!$H$5:$H$400,G8)+COUNTIF(G$4:G7,G8)+1,"0000")) | B8: 46492 | C8: SUP-0012 | E8: PO/27-28/002-01 | F8: =IF(E8="","",IFERROR(INDEX('PO Line Register'!$C$5:$C$400,MATCH(E8,'PO Line Register'!$A$5:$A$400,0)),"")) | G8: =IF(F8="","",INDEX('M_Material'!$B$5:$B$50,MATCH(F8,'M_Material'!$A$5:$A$50,0))) | H8: =IF(F8="","",INDEX('M_Material'!$D$5:$D$50,MATCH(F8,'M_Material'!$A$5:$A$50,0))) | I8: 2500 | J8: 1250 | K8: SHEET | L8: 25 | M8: 613.2 | N8: =IF(OR(L8="",H8=""),"",ROUND(L8*I8*J8*H8*'Settings'!$B$9,3)) | O8: =IF(N8="","",M8/N8-1) | P8: 68.2 | Q8: =IF(E8="","",IFERROR(INDEX('PO Line Register'!$J$5:$J$400,MATCH(E8,'PO Line Register'!$A$5:$A$400,0)),"")) | R8: =IF(E8="","",IFERROR(INDEX('PO Status'!$F$5:$F$100,MATCH(E8,'PO Status'!$A$5:$A$100,0)),0)-SUMIFS(M$4:M7,E$4:E7,E8)) | S8: =IF(R8="","",MAX(0,M8-R8)) | T8: =IF(C8="","",IF(F8="","NO OPEN PO LINE",IF(N(M8)<=0,"RECEIVED KG REQUIRED",IF(D8="","INVOICE NO REQUIRED",IF(S8>0,"WARN: EXCESS "&TEXT(S8,"0.0")&" kg - decide in Lot QC",IF(ABS(O8)>'Settings'!$B$10,"WARN: THEO VAR "&TEXT(O8,"+0.0%"),"READY"))))))

Sheet RM Move Entry
A1: RM ISSUE & RETURN ENTRY PAD
A2: ISSUE creates a batch. Returns / offcuts / damaged / scrap must quote an open batch of the same lot. Max available is shown on every row.
A3: Lot Balance: | B3: ='Lot Balance'!E3
A4: Move ID | B4: Move Date | C4: Movement | D4: Batch ID | E4: Material ID | F4: FIFO Lot | G4: Lot ID | H4: Override Reason | I4: Form | J4: Sheets | K4: Weight kg | L4: Avail kg | M4: Avail Sh | N4: Stock Effect kg | O4: Rate Rs | P4: Machine ID | Q4: Issued To | R4: Ready / issues
A5: =IF(C5="","",IF(C5="ISSUE","ISS",IF(C5="RETURN-OFFCUT","OFC",IF(C5="STORES-SCRAP","SCR","RET")))&"-"&'Settings'!$B$6&"-"&TEXT(COUNTA('RM Move Register'!$A$5:$A$400)+ROW()-4,"000000")) | B5: 46492 | C5: ISSUE | D5: =IF(C5="ISSUE",A5,"") | E5: GPSP-1.6 | F5: {=IFERROR(INDEX('Lot Balance'!$A$5:$A$100,MATCH(1,('Lot Balance'!$B$5:$B$100=E5)*('Lot Balance'!$E$5:$E$100="Yes")*('Lot Balance'!$K$5:$K$100>0),0)),"")} | G5: GP-2728-0001 | I5: SHEET | J5: 8 | K5: 300 | L5: =IF(G5="","",IFERROR(INDEX('Lot Balance'!$K$5:$K$100,MATCH(G5,'Lot Balance'!$A$5:$A$100,0)),0)-SUMIFS(K$4:K4,G$4:G4,G5,C$4:C4,"ISSUE")) | M5: =IF(G5="","",IFERROR(INDEX('Lot Balance'!$L$5:$L$100,MATCH(G5,'Lot Balance'!$A$5:$A$100,0)),0)-SUMIFS(J$4:J4,G$4:G4,G5,C$4:C4,"ISSUE")) | N5: =IF(C5="","",IF(C5="ISSUE",-K5,IF(OR(C5="RETURN-USABLE",C5="RETURN-OFFCUT"),K5,0))) | O5: =IF(G5="","",IFERROR(INDEX('GRN Register'!$Q$5:$Q$400,MATCH(G5,'GRN Register'!$A$5:$A$400,0)),"")) | P5: MC-01 | Q5: PER-007 | R5: =IF(C5="","",IF(IFERROR(INDEX('Lot Balance'!$E$5:$E$100,MATCH(G5,'Lot Balance'!$A$5:$A$100,0)),"No")="No","LOT NOT ISSUE-ELIGIBLE (QC)",IF(AND(C5="ISSUE",K5>L5),"EXCEEDS AVAILABLE: max "&TEXT(L5,"0.000")&" kg / "&M5&" sh",IF(AND(C5<>"ISSUE",D5=""),"RETURN MUST QUOTE BATCH",IF(AND(C5="ISSUE",G5<>F5,H5=""),"WARN: NOT FIFO - override reason required","READY")))))
A6: =IF(C6="","",IF(C6="ISSUE","ISS",IF(C6="RETURN-OFFCUT","OFC",IF(C6="STORES-SCRAP","SCR","RET")))&"-"&'Settings'!$B$6&"-"&TEXT(COUNTA('RM Move Register'!$A$5:$A$400)+ROW()-4,"000000")) | B6: 46492 | C6: ISSUE | D6: =IF(C6="ISSUE",A6,"") | E6: GPSP-1.6 | F6: {=IFERROR(INDEX('Lot Balance'!$A$5:$A$100,MATCH(1,('Lot Balance'!$B$5:$B$100=E6)*('Lot Balance'!$E$5:$E$100="Yes")*('Lot Balance'!$K$5:$K$100>0),0)),"")} | G6: GP-2728-0001 | I6: SHEET | J6: 25 | K6: 980 | L6: =IF(G6="","",IFERROR(INDEX('Lot Balance'!$K$5:$K$100,MATCH(G6,'Lot Balance'!$A$5:$A$100,0)),0)-SUMIFS(K$4:K5,G$4:G5,G6,C$4:C5,"ISSUE")) | M6: =IF(G6="","",IFERROR(INDEX('Lot Balance'!$L$5:$L$100,MATCH(G6,'Lot Balance'!$A$5:$A$100,0)),0)-SUMIFS(J$4:J5,G$4:G5,G6,C$4:C5,"ISSUE")) | N6: =IF(C6="","",IF(C6="ISSUE",-K6,IF(OR(C6="RETURN-USABLE",C6="RETURN-OFFCUT"),K6,0))) | O6: =IF(G6="","",IFERROR(INDEX('GRN Register'!$Q$5:$Q$400,MATCH(G6,'GRN Register'!$A$5:$A$400,0)),"")) | P6: MC-03 | Q6: PER-011 | R6: =IF(C6="","",IF(IFERROR(INDEX('Lot Balance'!$E$5:$E$100,MATCH(G6,'Lot Balance'!$A$5:$A$100,0)),"No")="No","LOT NOT ISSUE-ELIGIBLE (QC)",IF(AND(C6="ISSUE",K6>L6),"EXCEEDS AVAILABLE: max "&TEXT(L6,"0.000")&" kg / "&M6&" sh",IF(AND(C6<>"ISSUE",D6=""),"RETURN MUST QUOTE BATCH",IF(AND(C6="ISSUE",G6<>F6,H6=""),"WARN: NOT FIFO - override reason required","READY")))))
A7: =IF(C7="","",IF(C7="ISSUE","ISS",IF(C7="RETURN-OFFCUT","OFC",IF(C7="STORES-SCRAP","SCR","RET")))&"-"&'Settings'!$B$6&"-"&TEXT(COUNTA('RM Move Register'!$A$5:$A$400)+ROW()-4,"000000")) | B7: 46492 | C7: ISSUE | D7: =IF(C7="ISSUE",A7,"") | E7: CRCA-1.0 | F7: {=IFERROR(INDEX('Lot Balance'!$A$5:$A$100,MATCH(1,('Lot Balance'!$B$5:$B$100=E7)*('Lot Balance'!$E$5:$E$100="Yes")*('Lot Balance'!$K$5:$K$100>0),0)),"")} | G7: CR-2728-0001 | I7: SHEET | J7: 5 | K7: 122.6 | L7: =IF(G7="","",IFERROR(INDEX('Lot Balance'!$K$5:$K$100,MATCH(G7,'Lot Balance'!$A$5:$A$100,0)),0)-SUMIFS(K$4:K6,G$4:G6,G7,C$4:C6,"ISSUE")) | M7: =IF(G7="","",IFERROR(INDEX('Lot Balance'!$L$5:$L$100,MATCH(G7,'Lot Balance'!$A$5:$A$100,0)),0)-SUMIFS(J$4:J6,G$4:G6,G7,C$4:C6,"ISSUE")) | N7: =IF(C7="","",IF(C7="ISSUE",-K7,IF(OR(C7="RETURN-USABLE",C7="RETURN-OFFCUT"),K7,0))) | O7: =IF(G7="","",IFERROR(INDEX('GRN Register'!$Q$5:$Q$400,MATCH(G7,'GRN Register'!$A$5:$A$400,0)),"")) | P7: MC-02 | Q7: PER-003 | R7: =IF(C7="","",IF(IFERROR(INDEX('Lot Balance'!$E$5:$E$100,MATCH(G7,'Lot Balance'!$A$5:$A$100,0)),"No")="No","LOT NOT ISSUE-ELIGIBLE (QC)",IF(AND(C7="ISSUE",K7>L7),"EXCEEDS AVAILABLE: max "&TEXT(L7,"0.000")&" kg / "&M7&" sh",IF(AND(C7<>"ISSUE",D7=""),"RETURN MUST QUOTE BATCH",IF(AND(C7="ISSUE",G7<>F7,H7=""),"WARN: NOT FIFO - override reason required","READY")))))
A8: =IF(C8="","",IF(C8="ISSUE","ISS",IF(C8="RETURN-OFFCUT","OFC",IF(C8="STORES-SCRAP","SCR","RET")))&"-"&'Settings'!$B$6&"-"&TEXT(COUNTA('RM Move Register'!$A$5:$A$400)+ROW()-4,"000000")) | B8: 46492 | C8: ISSUE | D8: =IF(C8="ISSUE",A8,"") | E8: GPSP-1.6 | F8: {=IFERROR(INDEX('Lot Balance'!$A$5:$A$100,MATCH(1,('Lot Balance'!$B$5:$B$100=E8)*('Lot Balance'!$E$5:$E$100="Yes")*('Lot Balance'!$K$5:$K$100>0),0)),"")} | G8: GP-2728-0003 | I8: SHEET | J8: 4 | K8: 157.3 | L8: =IF(G8="","",IFERROR(INDEX('Lot Balance'!$K$5:$K$100,MATCH(G8,'Lot Balance'!$A$5:$A$100,0)),0)-SUMIFS(K$4:K7,G$4:G7,G8,C$4:C7,"ISSUE")) | M8: =IF(G8="","",IFERROR(INDEX('Lot Balance'!$L$5:$L$100,MATCH(G8,'Lot Balance'!$A$5:$A$100,0)),0)-SUMIFS(J$4:J7,G$4:G7,G8,C$4:C7,"ISSUE")) | N8: =IF(C8="","",IF(C8="ISSUE",-K8,IF(OR(C8="RETURN-USABLE",C8="RETURN-OFFCUT"),K8,0))) | O8: =IF(G8="","",IFERROR(INDEX('GRN Register'!$Q$5:$Q$400,MATCH(G8,'GRN Register'!$A$5:$A$400,0)),"")) | P8: MC-01 | Q8: PER-007 | R8: =IF(C8="","",IF(IFERROR(INDEX('Lot Balance'!$E$5:$E$100,MATCH(G8,'Lot Balance'!$A$5:$A$100,0)),"No")="No","LOT NOT ISSUE-ELIGIBLE (QC)",IF(AND(C8="ISSUE",K8>L8),"EXCEEDS AVAILABLE: max "&TEXT(L8,"0.000")&" kg / "&M8&" sh",IF(AND(C8<>"ISSUE",D8=""),"RETURN MUST QUOTE BATCH",IF(AND(C8="ISSUE",G8<>F8,H8=""),"WARN: NOT FIFO - override reason required","READY")))))
A9: =IF(C9="","",IF(C9="ISSUE","ISS",IF(C9="RETURN-OFFCUT","OFC",IF(C9="STORES-SCRAP","SCR","RET")))&"-"&'Settings'!$B$6&"-"&TEXT(COUNTA('RM Move Register'!$A$5:$A$400)+ROW()-4,"000000")) | B9: 46492 | C9: RETURN-OFFCUT | D9: ISS-2728-000002 | E9: GPSP-1.2 | G9: GP-2728-0002 | I9: OFFCUT | J9: 0 | K9: 12.5 | L9: =IF(G9="","",IFERROR(INDEX('Lot Balance'!$K$5:$K$100,MATCH(G9,'Lot Balance'!$A$5:$A$100,0)),0)-SUMIFS(K$4:K8,G$4:G8,G9,C$4:C8,"ISSUE")) | M9: =IF(G9="","",IFERROR(INDEX('Lot Balance'!$L$5:$L$100,MATCH(G9,'Lot Balance'!$A$5:$A$100,0)),0)-SUMIFS(J$4:J8,G$4:G8,G9,C$4:C8,"ISSUE")) | N9: =IF(C9="","",IF(C9="ISSUE",-K9,IF(OR(C9="RETURN-USABLE",C9="RETURN-OFFCUT"),K9,0))) | O9: =IF(G9="","",IFERROR(INDEX('GRN Register'!$Q$5:$Q$400,MATCH(G9,'GRN Register'!$A$5:$A$400,0)),"")) | Q9: PER-011 | R9: =IF(C9="","",IF(IFERROR(INDEX('Lot Balance'!$E$5:$E$100,MATCH(G9,'Lot Balance'!$A$5:$A$100,0)),"No")="No","LOT NOT ISSUE-ELIGIBLE (QC)",IF(AND(C9="ISSUE",K9>L9),"EXCEEDS AVAILABLE: max "&TEXT(L9,"0.000")&" kg / "&M9&" sh",IF(AND(C9<>"ISSUE",D9=""),"RETURN MUST QUOTE BATCH",IF(AND(C9="ISSUE",G9<>F9,H9=""),"WARN: NOT FIFO - override reason required","READY")))))

Sheet Cons Entry
A1: CONSUMABLE ISSUE / RETURN PAD
A2: One row per item handed out or returned. Issue above balance is blocked.
A4: Cons Move ID | B4: Move Date | C4: Movement | D4: Item ID | E4: Item Name | F4: Qty | G4: Balance Before | H4: Avg Rate Rs | I4: Value Rs | J4: Issued To | K4: Where Used | L4: Ready / issues
A5: =IF(C5="","","CI-"&'Settings'!$B$6&"-"&TEXT(COUNTA('Cons Issue Register'!$A$5:$A$400)+ROW()-4,"000000")) | B5: 46492 | C5: ISSUE | D5: ABR-001 | E5: =IF(D5="","",IFERROR(INDEX('Cons Balance'!$B$5:$B$100,MATCH(D5,'Cons Balance'!$A$5:$A$100,0)),"?")) | F5: 30 | G5: =IF(D5="","",IFERROR(INDEX('Cons Balance'!$G$5:$G$100,MATCH(D5,'Cons Balance'!$A$5:$A$100,0)),0)-SUMIFS(F$4:F4,D$4:D4,D5,C$4:C4,"ISSUE")) | H5: =IF(D5="","",IFERROR(INDEX('Cons Balance'!$H$5:$H$100,MATCH(D5,'Cons Balance'!$A$5:$A$100,0)),0)) | I5: =IF(F5="","",ROUND(IF(C5="ISSUE",-1,1)*F5*H5,2)) | J5: PER-007 | K5: MC-01 SLTL Laser | L5: =IF(C5="","",IF(E5="?","ITEM NOT IN MASTER",IF(AND(C5="ISSUE",F5>G5),"EXCEEDS BALANCE: max "&G5,IF(K5="","WHERE USED REQUIRED","READY"))))
A6: =IF(C6="","","CI-"&'Settings'!$B$6&"-"&TEXT(COUNTA('Cons Issue Register'!$A$5:$A$400)+ROW()-4,"000000")) | B6: 46492 | C6: ISSUE | D6: GAS-001 | E6: =IF(D6="","",IFERROR(INDEX('Cons Balance'!$B$5:$B$100,MATCH(D6,'Cons Balance'!$A$5:$A$100,0)),"?")) | F6: 40 | G6: =IF(D6="","",IFERROR(INDEX('Cons Balance'!$G$5:$G$100,MATCH(D6,'Cons Balance'!$A$5:$A$100,0)),0)-SUMIFS(F$4:F5,D$4:D5,D6,C$4:C5,"ISSUE")) | H6: =IF(D6="","",IFERROR(INDEX('Cons Balance'!$H$5:$H$100,MATCH(D6,'Cons Balance'!$A$5:$A$100,0)),0)) | I6: =IF(F6="","",ROUND(IF(C6="ISSUE",-1,1)*F6*H6,2)) | J6: PER-030 | K6: Fabrication Bay | L6: =IF(C6="","",IF(E6="?","ITEM NOT IN MASTER",IF(AND(C6="ISSUE",F6>G6),"EXCEEDS BALANCE: max "&G6,IF(K6="","WHERE USED REQUIRED","READY"))))
A7: =IF(C7="","","CI-"&'Settings'!$B$6&"-"&TEXT(COUNTA('Cons Issue Register'!$A$5:$A$400)+ROW()-4,"000000")) | B7: 46492 | C7: ISSUE | D7: WLD-003 | E7: =IF(D7="","",IFERROR(INDEX('Cons Balance'!$B$5:$B$100,MATCH(D7,'Cons Balance'!$A$5:$A$100,0)),"?")) | F7: 10 | G7: =IF(D7="","",IFERROR(INDEX('Cons Balance'!$G$5:$G$100,MATCH(D7,'Cons Balance'!$A$5:$A$100,0)),0)-SUMIFS(F$4:F6,D$4:D6,D7,C$4:C6,"ISSUE")) | H7: =IF(D7="","",IFERROR(INDEX('Cons Balance'!$H$5:$H$100,MATCH(D7,'Cons Balance'!$A$5:$A$100,0)),0)) | I7: =IF(F7="","",ROUND(IF(C7="ISSUE",-1,1)*F7*H7,2)) | J7: PER-030 | L7: =IF(C7="","",IF(E7="?","ITEM NOT IN MASTER",IF(AND(C7="ISSUE",F7>G7),"EXCEEDS BALANCE: max "&G7,IF(K7="","WHERE USED REQUIRED","READY"))))
A8: =IF(C8="","","CI-"&'Settings'!$B$6&"-"&TEXT(COUNTA('Cons Issue Register'!$A$5:$A$400)+ROW()-4,"000000")) | B8: 46492 | C8: RETURN | D8: ABR-004 | E8: =IF(D8="","",IFERROR(INDEX('Cons Balance'!$B$5:$B$100,MATCH(D8,'Cons Balance'!$A$5:$A$100,0)),"?")) | F8: 2 | G8: =IF(D8="","",IFERROR(INDEX('Cons Balance'!$G$5:$G$100,MATCH(D8,'Cons Balance'!$A$5:$A$100,0)),0)-SUMIFS(F$4:F7,D$4:D7,D8,C$4:C7,"ISSUE")) | H8: =IF(D8="","",IFERROR(INDEX('Cons Balance'!$H$5:$H$100,MATCH(D8,'Cons Balance'!$A$5:$A$100,0)),0)) | I8: =IF(F8="","",ROUND(IF(C8="ISSUE",-1,1)*F8*H8,2)) | J8: PER-003 | K8: MC-02 Amada Punching | L8: =IF(C8="","",IF(E8="?","ITEM NOT IN MASTER",IF(AND(C8="ISSUE",F8>G8),"EXCEEDS BALANCE: max "&G8,IF(K8="","WHERE USED REQUIRED","READY"))))

Sheet Adjust Entry
A1: AUTHORISED STOCK-ADJUSTMENT PAD
A2: Only for genuine corrections. Reason code, reference and an approver different from the requester are mandatory.
A4: Adj ID | B4: Adj Date | C4: Stock Type | D4: Lot / Item ID | E4: Direction | F4: Adj kg / Qty | G4: Available | H4: Rate Rs | I4: Value Rs | J4: Reason Code | K4: Reference | L4: Requested By | M4: Approved By | N4: Ready / issues
A5: =IF(C5="","","ADJ-"&'Settings'!$B$6&"-"&TEXT(COUNTA('Adjust Register'!$A$5:$A$400)+ROW()-4,"00000")) | B5: 46492 | C5: RM-LOT | D5: GP-2728-0003 | E5: DECREASE | F5: 2.6 | G5: =IF(D5="","",IF(C5="RM-LOT",IFERROR(INDEX('Lot Balance'!$K$5:$K$100,MATCH(D5,'Lot Balance'!$A$5:$A$100,0)),0),IFERROR(INDEX('Cons Balance'!$G$5:$G$100,MATCH(D5,'Cons Balance'!$A$5:$A$100,0)),0))) | H5: =IF(D5="","",IF(C5="RM-LOT",IFERROR(INDEX('Lot Balance'!$M$5:$M$100,MATCH(D5,'Lot Balance'!$A$5:$A$100,0)),0),IFERROR(INDEX('Cons Balance'!$H$5:$H$100,MATCH(D5,'Cons Balance'!$A$5:$A$100,0)),0))) | I5: =IF(F5="","",ROUND(IF(E5="DECREASE",-1,1)*F5*H5,2)) | J5: ADJ-WGT | K5: Weighbridge slip WB-131 | L5: PER-015 | M5: PER-018 | N5: =IF(C5="","",IF(J5="","REASON CODE REQUIRED",IF(K5="","REFERENCE REQUIRED",IF(OR(M5="",M5=L5),"INDEPENDENT APPROVER REQUIRED",IF(AND(E5="DECREASE",F5>G5),"EXCEEDS AVAILABLE",IF(ABS(I5)>'Settings'!$B$13,"WARN: above limit - MD approval","READY"))))))
A6: =IF(C6="","","ADJ-"&'Settings'!$B$6&"-"&TEXT(COUNTA('Adjust Register'!$A$5:$A$400)+ROW()-4,"00000")) | B6: 46492 | C6: CONSUMABLE | D6: GAS-001 | E6: INCREASE | F6: 10 | G6: =IF(D6="","",IF(C6="RM-LOT",IFERROR(INDEX('Lot Balance'!$K$5:$K$100,MATCH(D6,'Lot Balance'!$A$5:$A$100,0)),0),IFERROR(INDEX('Cons Balance'!$G$5:$G$100,MATCH(D6,'Cons Balance'!$A$5:$A$100,0)),0))) | H6: =IF(D6="","",IF(C6="RM-LOT",IFERROR(INDEX('Lot Balance'!$M$5:$M$100,MATCH(D6,'Lot Balance'!$A$5:$A$100,0)),0),IFERROR(INDEX('Cons Balance'!$H$5:$H$100,MATCH(D6,'Cons Balance'!$A$5:$A$100,0)),0))) | I6: =IF(F6="","",ROUND(IF(E6="DECREASE",-1,1)*F6*H6,2)) | L6: PER-015 | M6: PER-015 | N6: =IF(C6="","",IF(J6="","REASON CODE REQUIRED",IF(K6="","REFERENCE REQUIRED",IF(OR(M6="",M6=L6),"INDEPENDENT APPROVER REQUIRED",IF(AND(E6="DECREASE",F6>G6),"EXCEEDS AVAILABLE",IF(ABS(I6)>'Settings'!$B$13,"WARN: above limit - MD approval","READY"))))))
A7: =IF(C7="","","ADJ-"&'Settings'!$B$6&"-"&TEXT(COUNTA('Adjust Register'!$A$5:$A$400)+ROW()-4,"00000")) | B7: 46492 | C7: RM-LOT | D7: HR-2728-0001 | E7: DECREASE | F7: 30 | G7: =IF(D7="","",IF(C7="RM-LOT",IFERROR(INDEX('Lot Balance'!$K$5:$K$100,MATCH(D7,'Lot Balance'!$A$5:$A$100,0)),0),IFERROR(INDEX('Cons Balance'!$G$5:$G$100,MATCH(D7,'Cons Balance'!$A$5:$A$100,0)),0))) | H7: =IF(D7="","",IF(C7="RM-LOT",IFERROR(INDEX('Lot Balance'!$M$5:$M$100,MATCH(D7,'Lot Balance'!$A$5:$A$100,0)),0),IFERROR(INDEX('Cons Balance'!$H$5:$H$100,MATCH(D7,'Cons Balance'!$A$5:$A$100,0)),0))) | I7: =IF(F7="","",ROUND(IF(E7="DECREASE",-1,1)*F7*H7,2)) | J7: ADJ-DMG | K7: Damage note DN-07 | L7: PER-015 | N7: =IF(C7="","",IF(J7="","REASON CODE REQUIRED",IF(K7="","REFERENCE REQUIRED",IF(OR(M7="",M7=L7),"INDEPENDENT APPROVER REQUIRED",IF(AND(E7="DECREASE",F7>G7),"EXCEEDS AVAILABLE",IF(ABS(I7)>'Settings'!$B$13,"WARN: above limit - MD approval","READY"))))))

Sheet PO Header Register
A1: PO HEADER REGISTER - values only
A2: Posted from PO Entry. Status changes are new status lines, never edits.
A4: PO No | B4: PO Date | C4: Supplier ID | D4: Supplier Name | E4: Delivery By | F4: Pay Days | G4: Delivery Location | H4: Approved By | I4: PO Status | J4: Posted At | K4: Posted By | L4: Entry Source
A5: PO/27-28/001 | B5: 46479 | C5: SUP-0007 | D5: Supplier A (masked) | E5: 46489 | F5: 30 | G5: ISKO Factory | H5: PER-018 | I5: OPEN | J5: 46479.462 | K5: PER-015 | L5: PAD
A6: PO/27-28/002 | B6: 46480 | C6: SUP-0012 | D6: Supplier B (masked) | E6: 46491 | F6: 45 | G6: ISKO Factory | H6: PER-018 | I6: OPEN | J6: 46480.694 | K6: PER-015 | L6: PAD

Sheet PO Line Register
A1: PO LINE REGISTER - values only
A2: Received / pending are NOT stored here - see PO Status.
A4: PO Line ID | B4: PO No | C4: Item ID | D4: Grade | E4: Thk mm | F4: L mm | G4: W mm | H4: Ordered kg | I4: Unit | J4: Rate Rs | K4: Line Value Rs | L4: Due Date | M4: Posted At
A5: PO/27-28/001-01 | B5: PO/27-28/001 | C5: GPSP-1.6 | D5: GPSP | E5: 1.6 | F5: 2500 | G5: 1250 | H5: 3000 | I5: KGS | J5: 74.5 | K5: 223500 | L5: 46489 | M5: 46479.462
A6: PO/27-28/001-02 | B6: PO/27-28/001 | C6: GPSP-1.2 | D6: GPSP | E6: 1.2 | F6: 2500 | G6: 1250 | H6: 2400 | I6: KGS | J6: 74.5 | K6: 178800 | L6: 46489 | M6: 46479.462
A7: PO/27-28/002-01 | B7: PO/27-28/002 | C7: CRCA-1.0 | D7: CRCA | E7: 1 | F7: 2500 | G7: 1250 | H7: 1500 | I7: KGS | J7: 68.2 | K7: 102300 | L7: 46491 | M7: 46480.694

Sheet GRN Register
A1: GRN REGISTER - one row per lot, values only
A2: Receipt facts only. QC decisions are in Lot QC Register.
A4: Lot ID | B4: GRN Date | C4: Supplier ID | D4: Supplier Inv No | E4: Invoice Date | F4: PO Line ID | G4: Material ID | H4: Grade Code | I4: Thk mm | J4: L mm | K4: W mm | L4: Form | M4: Sheets | N4: Received kg | O4: Theo kg | P4: Theo Var % | Q4: Bill Rate Rs | R4: PO Rate Rs | S4: Excess kg | T4: Lot Value Rs | U4: Posted At | V4: Entry Source
A5: HR-2728-0001 | B5: 46478 | C5: SUP-0012 | D5: OPENING | E5: 46478 | F5: NO-PO | G5: HRCA-2.0 | H5: HR | I5: 2 | J5: 2500 | K5: 1250 | L5: SHEET | M5: 9 | N5: 640.2 | O5: 441.6 | Q5: 66.1 | S5: 0 | T5: 42317.22 | U5: 46478.375 | V5: OPENING
A6: GP-2728-0001 | B6: 46485 | C6: SUP-0007 | D6: INV/3381 | E6: 46484 | F6: PO/27-28/001-01 | G6: GPSP-1.6 | H6: GP | I6: 1.6 | J6: 2500 | K6: 1250 | L6: SHEET | M6: 40 | N6: 1575.5 | O6: 1570 | P6: 0.0035 | Q6: 74.5 | R6: 74.5 | S6: 0 | T6: 117374.75 | U6: 46485.507 | V6: PAD
A7: GP-2728-0002 | B7: 46485 | C7: SUP-0007 | D7: INV/3381 | E7: 46484 | F7: PO/27-28/001-02 | G7: GPSP-1.2 | H7: GP | I7: 1.2 | J7: 2500 | K7: 1250 | L7: SHEET | M7: 60 | N7: 1750 | O7: 1766.25 | P7: -0.0092 | Q7: 74.5 | R7: 74.5 | S7: 0 | T7: 130375 | U7: 46485.507 | V7: PAD
A8: CR-2728-0001 | B8: 46489 | C8: SUP-0012 | D8: B-77120 | E8: 46489 | F8: PO/27-28/002-01 | G8: CRCA-1.0 | H8: CR | I8: 1 | J8: 2500 | K8: 1250 | L8: SHEET | M8: 30 | N8: 736 | O8: 735.94 | P8: 0.0001 | Q8: 68.2 | R8: 68.2 | S8: 0 | T8: 50195.2 | U8: 46489.625 | V8: PAD
A9: GP-2728-0003 | B9: 46490 | C9: SUP-0007 | D9: INV/3402 | E9: 46490 | F9: PO/27-28/001-01 | G9: GPSP-1.6 | H9: GP | I9: 1.6 | J9: 2500 | K9: 1250 | L9: SHEET | M9: 30 | N9: 1180 | O9: 1177.5 | P9: 0.0021 | Q9: 74.5 | R9: 74.5 | S9: 0 | T9: 87910 | U9: 46490.479 | V9: PAD

Sheet Lot QC Register
A1: LOT QC REGISTER - QC and excess decisions (append-only)
A2: The latest decision per lot decides whether it can be issued.
A4: QC Event ID | B4: Lot ID | C4: QC Date | D4: QC Status | E4: Rejected kg | F4: Rejected Sheets | G4: Excess Decision | H4: Decided By | I4: Accepted kg | J4: Accepted Sheets | K4: Posted At
A5: QC-2728-000001 | B5: HR-2728-0001 | C5: 46478 | D5: ACCEPTED | E5: 0 | F5: 0 | H5: PER-018 | I5: 640.2 | J5: 9 | K5: 46478.396
A6: QC-2728-000002 | B6: GP-2728-0001 | C6: 46485 | D6: ACCEPTED | E6: 0 | F6: 0 | H6: PER-018 | I6: 1575.5 | J6: 40 | K6: 46485.667
A7: QC-2728-000003 | B7: GP-2728-0002 | C7: 46486 | D7: ACCEPTED WITH REJECTION | E7: 26.4 | F7: 1 | H7: PER-018 | I7: 1723.6 | J7: 59 | K7: 46486.427
A8: QC-2728-000004 | B8: CR-2728-0001 | C8: 46489 | D8: HOLD | E8: 0 | F8: 0 | H8: PER-018 | I8: 0 | J8: 0 | K8: 46489.708
A9: QC-2728-000005 | B9: GP-2728-0003 | C9: 46490 | D9: ACCEPTED | E9: 0 | F9: 0 | H9: PER-018 | I9: 1180 | J9: 30 | K9: 46490.625

Sheet RM Move Register
A1: RM MOVEMENT REGISTER - values only
A2: ISSUE line = batch (Batch ID = Move ID). Returns and scrap quote the batch. Corrections = reversal rows.
A4: Move ID | B4: Move Date | C4: Movement | D4: Batch ID | E4: Material ID | F4: Lot ID | G4: Form | H4: Sheets | I4: Weight kg | J4: Stock Effect kg | K4: Stock Effect Sh | L4: Rate Rs | M4: Value Rs | N4: Machine ID | O4: Issued To | P4: Purpose | Q4: Avail kg Before | R4: Posted At | S4: Reverses ID
A5: ISS-2728-000001 | B5: 46489 | C5: ISSUE | D5: ISS-2728-000001 | E5: GPSP-1.6 | F5: GP-2728-0001 | G5: SHEET | H5: 12 | I5: 471 | J5: -471 | K5: -12 | L5: 74.5 | M5: -35089.5 | N5: MC-01 | O5: PER-007 | P5: PRD-A12 | Q5: 1575.5 | R5: 46489.389
A6: ISS-2728-000002 | B6: 46489 | C6: ISSUE | D6: ISS-2728-000002 | E6: GPSP-1.2 | F6: GP-2728-0002 | G6: SHEET | H6: 15 | I6: 420 | J6: -420 | K6: -15 | L6: 74.5 | M6: -31290 | N6: MC-03 | O6: PER-011 | P6: PRD-B07 | Q6: 1723.6 | R6: 46489.392
A7: OFC-2728-000003 | B7: 46490 | C7: RETURN-OFFCUT | D7: ISS-2728-000001 | E7: GPSP-1.6 | F7: GP-2728-0001 | G7: OFFCUT | H7: 0 | I7: 18.4 | J7: 18.4 | K7: 0 | L7: 74.5 | M7: 1370.8 | O7: PER-007 | Q7: 1104.5 | R7: 46490.715
A8: ISS-2728-000004 | B8: 46490 | C8: ISSUE | D8: ISS-2728-000004 | E8: HRCA-2.0 | F8: HR-2728-0001 | G8: SHEET | H8: 3 | I8: 214.9 | J8: -214.9 | K8: -3 | L8: 66.1 | M8: -14204.89 | N8: MC-02 | O8: PER-003 | P8: PRD-C03 | Q8: 640.2 | R8: 46490.417

Sheet Cons Receipt Register
A1: CONSUMABLE RECEIPT REGISTER - values only
A2: Purchases and the one-time OPENING lines.
A4: Receipt ID | B4: Receipt Date | C4: Item ID | D4: Qty | E4: Bill Rate Rs | F4: Value Rs | G4: Receipt Type | H4: Supplier ID | I4: Bill No | J4: Posted At
A5: CR-2728-000001 | B5: 46478 | C5: ABR-001 | D5: 120 | E5: 23.3 | F5: =ROUND(D5*E5,2) | G5: OPENING | J5: 46478.375
A6: CR-2728-000002 | B6: 46478 | C6: WLD-003 | D6: 80 | E6: 148 | F6: =ROUND(D6*E6,2) | G6: OPENING | J6: 46478.375
A7: CR-2728-000003 | B7: 46478 | C7: GAS-001 | D7: 150 | E7: 15 | F7: =ROUND(D7*E7,2) | G7: OPENING | J7: 46478.375
A8: CR-2728-000004 | B8: 46486 | C8: ABR-004 | D8: 50 | E8: 64 | F8: =ROUND(D8*E8,2) | G8: PURCHASE | H8: SUP-0020 | I8: C-5512 | J8: 46486.583

Sheet Cons Issue Register
A1: CONSUMABLE ISSUE REGISTER - values only
A2: Issues and returns as separate rows. Rate = average at posting (frozen).
A4: Cons Move ID | B4: Move Date | C4: Movement | D4: Item ID | E4: Qty | F4: Stock Effect | G4: Rate Rs | H4: Value Rs | I4: Issued To | J4: Where Used | K4: Posted At
A5: CI-2728-000001 | B5: 46487 | C5: ISSUE | D5: ABR-001 | E5: 40 | F5: -40 | G5: 23.3 | H5: -932 | I5: PER-007 | J5: MC-01 SLTL Laser | K5: 46487.417
A6: CI-2728-000002 | B6: 46488 | C6: ISSUE | D6: GAS-001 | E6: 120 | F6: -120 | G6: 15 | H6: -1800 | I6: PER-030 | J6: Fabrication Bay | K6: 46488.375
A7: CI-2728-000003 | B7: 46489 | C7: RETURN | D7: ABR-001 | E7: 5 | F7: 5 | G7: 23.3 | H7: 116.5 | I7: PER-007 | J7: MC-01 SLTL Laser | K7: 46489.708

Sheet Adjust Register
A1: AUTHORISED STOCK ADJUSTMENT REGISTER
A2: Approved corrections only - reason, reference, independent approver. Not a count module.
A4: Adj ID | B4: Adj Date | C4: Stock Type | D4: Lot / Item ID | E4: Direction | F4: Adj kg / Qty | G4: Signed kg | H4: Rate Rs | I4: Value Rs | J4: Reason Code | K4: Reference | L4: Requested By | M4: Approved By | N4: Posted At
A5: ADJ-2728-00001 | B5: 46491 | C5: RM-LOT | D5: GP-2728-0002 | E5: DECREASE | F5: 4.2 | G5: =IF(E5="DECREASE",-F5,F5) | H5: 74.5 | I5: =ROUND(G5*H5,2) | J5: ADJ-WGT | K5: Weighbridge slip WB-118 | L5: PER-015 | M5: PER-018 | N5: 46491.5

Sheet PO Status
A1: PO STATUS - open PO lines (calculated)
A2: Ordered vs received; overdue lines feed the MIS exception list.
A4: PO Line ID | B4: Supplier ID | C4: Item ID | D4: Ordered kg | E4: Received kg | F4: Pending kg | G4: Due Date | H4: Overdue Days | I4: Status
A5: PO/27-28/001-01 | B5: =INDEX('PO Header Register'!$C$5:$C$400,MATCH(LEFT(A5,12),'PO Header Register'!$A$5:$A$400,0)) | C5: =INDEX('PO Line Register'!$C$5:$C$400,MATCH(A5,'PO Line Register'!$A$5:$A$400,0)) | D5: =INDEX('PO Line Register'!$H$5:$H$400,MATCH(A5,'PO Line Register'!$A$5:$A$400,0)) | E5: =SUMIFS('GRN Register'!$N$5:$N$400,'GRN Register'!$F$5:$F$400,A5) | F5: =MAX(0,D5-E5) | G5: =INDEX('PO Line Register'!$L$5:$L$400,MATCH(A5,'PO Line Register'!$A$5:$A$400,0)) | H5: =IF(F5>0,MAX(0,'Settings'!$B$7-G5),0) | I5: =IF(F5=0,"CLOSED - fully received",IF(H5>0,"OVERDUE "&H5&" d","OK"))
A6: PO/27-28/001-02 | B6: =INDEX('PO Header Register'!$C$5:$C$400,MATCH(LEFT(A6,12),'PO Header Register'!$A$5:$A$400,0)) | C6: =INDEX('PO Line Register'!$C$5:$C$400,MATCH(A6,'PO Line Register'!$A$5:$A$400,0)) | D6: =INDEX('PO Line Register'!$H$5:$H$400,MATCH(A6,'PO Line Register'!$A$5:$A$400,0)) | E6: =SUMIFS('GRN Register'!$N$5:$N$400,'GRN Register'!$F$5:$F$400,A6) | F6: =MAX(0,D6-E6) | G6: =INDEX('PO Line Register'!$L$5:$L$400,MATCH(A6,'PO Line Register'!$A$5:$A$400,0)) | H6: =IF(F6>0,MAX(0,'Settings'!$B$7-G6),0) | I6: =IF(F6=0,"CLOSED - fully received",IF(H6>0,"OVERDUE "&H6&" d","OK"))
A7: PO/27-28/002-01 | B7: =INDEX('PO Header Register'!$C$5:$C$400,MATCH(LEFT(A7,12),'PO Header Register'!$A$5:$A$400,0)) | C7: =INDEX('PO Line Register'!$C$5:$C$400,MATCH(A7,'PO Line Register'!$A$5:$A$400,0)) | D7: =INDEX('PO Line Register'!$H$5:$H$400,MATCH(A7,'PO Line Register'!$A$5:$A$400,0)) | E7: =SUMIFS('GRN Register'!$N$5:$N$400,'GRN Register'!$F$5:$F$400,A7) | F7: =MAX(0,D7-E7) | G7: =INDEX('PO Line Register'!$L$5:$L$400,MATCH(A7,'PO Line Register'!$A$5:$A$400,0)) | H7: =IF(F7>0,MAX(0,'Settings'!$B$7-G7),0) | I7: =IF(F7=0,"CLOSED - fully received",IF(H7>0,"OVERDUE "&H7&" d","OK"))

Sheet Lot Balance
A1: LOT BALANCE - open lots, oldest first (calculated)
A2: Rebuilt after posting (Refresh All). Every issue check reads this sheet.
A3: Rows at refresh | B3: 4 | C3: Live rows | D3: =COUNTA('RM Move Register'!$A$5:$A$400) | E3: =IF(D3=B3,"OK","STALE - Refresh All")
A4: Lot ID | B4: Material ID | C4: GRN Date | D4: QC Status | E4: Issue Eligible | F4: Accepted kg | G4: Accepted Sh | H4: Movement kg | I4: Movement Sh | J4: Adjust kg | K4: Available kg | L4: Available Sh | M4: Rate Rs | N4: Value Rs | O4: Age Days | P4: Status
A5: HR-2728-0001 | B5: =INDEX('GRN Register'!$G$5:$G$400,MATCH(A5,'GRN Register'!$A$5:$A$400,0)) | C5: =INDEX('GRN Register'!$B$5:$B$400,MATCH(A5,'GRN Register'!$A$5:$A$400,0)) | D5: =IFERROR(INDEX('Lot QC Register'!$D$5:$D$400,MATCH(A5,'Lot QC Register'!$B$5:$B$400,0)),"PENDING") | E5: =IF(OR(D5="ACCEPTED",D5="ACCEPTED WITH REJECTION"),"Yes","No") | F5: =SUMIFS('Lot QC Register'!$I$5:$I$400,'Lot QC Register'!$B$5:$B$400,A5) | G5: =SUMIFS('Lot QC Register'!$J$5:$J$400,'Lot QC Register'!$B$5:$B$400,A5) | H5: =SUMIFS('RM Move Register'!$J$5:$J$400,'RM Move Register'!$F$5:$F$400,A5) | I5: =SUMIFS('RM Move Register'!$K$5:$K$400,'RM Move Register'!$F$5:$F$400,A5) | J5: =SUMIFS('Adjust Register'!$G$5:$G$400,'Adjust Register'!$D$5:$D$400,A5) | K5: =ROUND(F5+H5+J5,3) | L5: =G5+I5 | M5: =INDEX('GRN Register'!$Q$5:$Q$400,MATCH(A5,'GRN Register'!$A$5:$A$400,0)) | N5: =ROUND(K5*M5,2) | O5: ='Settings'!$B$7-C5 | P5: =IF(K5<0,"BREACH - negative",IF(E5="No","NOT ISSUE-ELIGIBLE",IF(O5>90,"WARN: over 90 days","OK")))
A6: GP-2728-0001 | B6: =INDEX('GRN Register'!$G$5:$G$400,MATCH(A6,'GRN Register'!$A$5:$A$400,0)) | C6: =INDEX('GRN Register'!$B$5:$B$400,MATCH(A6,'GRN Register'!$A$5:$A$400,0)) | D6: =IFERROR(INDEX('Lot QC Register'!$D$5:$D$400,MATCH(A6,'Lot QC Register'!$B$5:$B$400,0)),"PENDING") | E6: =IF(OR(D6="ACCEPTED",D6="ACCEPTED WITH REJECTION"),"Yes","No") | F6: =SUMIFS('Lot QC Register'!$I$5:$I$400,'Lot QC Register'!$B$5:$B$400,A6) | G6: =SUMIFS('Lot QC Register'!$J$5:$J$400,'Lot QC Register'!$B$5:$B$400,A6) | H6: =SUMIFS('RM Move Register'!$J$5:$J$400,'RM Move Register'!$F$5:$F$400,A6) | I6: =SUMIFS('RM Move Register'!$K$5:$K$400,'RM Move Register'!$F$5:$F$400,A6) | J6: =SUMIFS('Adjust Register'!$G$5:$G$400,'Adjust Register'!$D$5:$D$400,A6) | K6: =ROUND(F6+H6+J6,3) | L6: =G6+I6 | M6: =INDEX('GRN Register'!$Q$5:$Q$400,MATCH(A6,'GRN Register'!$A$5:$A$400,0)) | N6: =ROUND(K6*M6,2) | O6: ='Settings'!$B$7-C6 | P6: =IF(K6<0,"BREACH - negative",IF(E6="No","NOT ISSUE-ELIGIBLE",IF(O6>90,"WARN: over 90 days","OK")))
A7: GP-2728-0002 | B7: =INDEX('GRN Register'!$G$5:$G$400,MATCH(A7,'GRN Register'!$A$5:$A$400,0)) | C7: =INDEX('GRN Register'!$B$5:$B$400,MATCH(A7,'GRN Register'!$A$5:$A$400,0)) | D7: =IFERROR(INDEX('Lot QC Register'!$D$5:$D$400,MATCH(A7,'Lot QC Register'!$B$5:$B$400,0)),"PENDING") | E7: =IF(OR(D7="ACCEPTED",D7="ACCEPTED WITH REJECTION"),"Yes","No") | F7: =SUMIFS('Lot QC Register'!$I$5:$I$400,'Lot QC Register'!$B$5:$B$400,A7) | G7: =SUMIFS('Lot QC Register'!$J$5:$J$400,'Lot QC Register'!$B$5:$B$400,A7) | H7: =SUMIFS('RM Move Register'!$J$5:$J$400,'RM Move Register'!$F$5:$F$400,A7) | I7: =SUMIFS('RM Move Register'!$K$5:$K$400,'RM Move Register'!$F$5:$F$400,A7) | J7: =SUMIFS('Adjust Register'!$G$5:$G$400,'Adjust Register'!$D$5:$D$400,A7) | K7: =ROUND(F7+H7+J7,3) | L7: =G7+I7 | M7: =INDEX('GRN Register'!$Q$5:$Q$400,MATCH(A7,'GRN Register'!$A$5:$A$400,0)) | N7: =ROUND(K7*M7,2) | O7: ='Settings'!$B$7-C7 | P7: =IF(K7<0,"BREACH - negative",IF(E7="No","NOT ISSUE-ELIGIBLE",IF(O7>90,"WARN: over 90 days","OK")))
A8: CR-2728-0001 | B8: =INDEX('GRN Register'!$G$5:$G$400,MATCH(A8,'GRN Register'!$A$5:$A$400,0)) | C8: =INDEX('GRN Register'!$B$5:$B$400,MATCH(A8,'GRN Register'!$A$5:$A$400,0)) | D8: =IFERROR(INDEX('Lot QC Register'!$D$5:$D$400,MATCH(A8,'Lot QC Register'!$B$5:$B$400,0)),"PENDING") | E8: =IF(OR(D8="ACCEPTED",D8="ACCEPTED WITH REJECTION"),"Yes","No") | F8: =SUMIFS('Lot QC Register'!$I$5:$I$400,'Lot QC Register'!$B$5:$B$400,A8) | G8: =SUMIFS('Lot QC Register'!$J$5:$J$400,'Lot QC Register'!$B$5:$B$400,A8) | H8: =SUMIFS('RM Move Register'!$J$5:$J$400,'RM Move Register'!$F$5:$F$400,A8) | I8: =SUMIFS('RM Move Register'!$K$5:$K$400,'RM Move Register'!$F$5:$F$400,A8) | J8: =SUMIFS('Adjust Register'!$G$5:$G$400,'Adjust Register'!$D$5:$D$400,A8) | K8: =ROUND(F8+H8+J8,3) | L8: =G8+I8 | M8: =INDEX('GRN Register'!$Q$5:$Q$400,MATCH(A8,'GRN Register'!$A$5:$A$400,0)) | N8: =ROUND(K8*M8,2) | O8: ='Settings'!$B$7-C8 | P8: =IF(K8<0,"BREACH - negative",IF(E8="No","NOT ISSUE-ELIGIBLE",IF(O8>90,"WARN: over 90 days","OK")))
A9: GP-2728-0003 | B9: =INDEX('GRN Register'!$G$5:$G$400,MATCH(A9,'GRN Register'!$A$5:$A$400,0)) | C9: =INDEX('GRN Register'!$B$5:$B$400,MATCH(A9,'GRN Register'!$A$5:$A$400,0)) | D9: =IFERROR(INDEX('Lot QC Register'!$D$5:$D$400,MATCH(A9,'Lot QC Register'!$B$5:$B$400,0)),"PENDING") | E9: =IF(OR(D9="ACCEPTED",D9="ACCEPTED WITH REJECTION"),"Yes","No") | F9: =SUMIFS('Lot QC Register'!$I$5:$I$400,'Lot QC Register'!$B$5:$B$400,A9) | G9: =SUMIFS('Lot QC Register'!$J$5:$J$400,'Lot QC Register'!$B$5:$B$400,A9) | H9: =SUMIFS('RM Move Register'!$J$5:$J$400,'RM Move Register'!$F$5:$F$400,A9) | I9: =SUMIFS('RM Move Register'!$K$5:$K$400,'RM Move Register'!$F$5:$F$400,A9) | J9: =SUMIFS('Adjust Register'!$G$5:$G$400,'Adjust Register'!$D$5:$D$400,A9) | K9: =ROUND(F9+H9+J9,3) | L9: =G9+I9 | M9: =INDEX('GRN Register'!$Q$5:$Q$400,MATCH(A9,'GRN Register'!$A$5:$A$400,0)) | N9: =ROUND(K9*M9,2) | O9: ='Settings'!$B$7-C9 | P9: =IF(K9<0,"BREACH - negative",IF(E9="No","NOT ISSUE-ELIGIBLE",IF(O9>90,"WARN: over 90 days","OK")))

Sheet Cons Balance
A1: CONSUMABLE BALANCE (calculated)
A2: Stock = receipts + net issues + approved adjustments. Re-order flag from minimum level.
A4: Item ID | B4: Item Name | C4: Unit | D4: Received | E4: Net Issued | F4: Adjusted | G4: Balance | H4: Avg Rate Rs | I4: Value Rs | J4: Min Level | K4: Status
A5: ABR-001 | B5: =INDEX('M_Consumable'!$B$5:$B$50,MATCH(A5,'M_Consumable'!$A$5:$A$50,0)) | C5: =INDEX('M_Consumable'!$D$5:$D$50,MATCH(A5,'M_Consumable'!$A$5:$A$50,0)) | D5: =SUMIFS('Cons Receipt Register'!$D$5:$D$400,'Cons Receipt Register'!$C$5:$C$400,A5) | E5: =SUMIFS('Cons Issue Register'!$F$5:$F$400,'Cons Issue Register'!$D$5:$D$400,A5) | F5: =SUMIFS('Adjust Register'!$G$5:$G$400,'Adjust Register'!$D$5:$D$400,A5) | G5: =D5+E5+F5 | H5: =IFERROR(SUMIFS('Cons Receipt Register'!$F$5:$F$400,'Cons Receipt Register'!$C$5:$C$400,A5)/D5,0) | I5: =ROUND(G5*H5,2) | J5: =INDEX('M_Consumable'!$E$5:$E$50,MATCH(A5,'M_Consumable'!$A$5:$A$50,0)) | K5: =IF(G5<0,"NEGATIVE",IF(G5<=J5,"REORDER","OK"))
A6: ABR-004 | B6: =INDEX('M_Consumable'!$B$5:$B$50,MATCH(A6,'M_Consumable'!$A$5:$A$50,0)) | C6: =INDEX('M_Consumable'!$D$5:$D$50,MATCH(A6,'M_Consumable'!$A$5:$A$50,0)) | D6: =SUMIFS('Cons Receipt Register'!$D$5:$D$400,'Cons Receipt Register'!$C$5:$C$400,A6) | E6: =SUMIFS('Cons Issue Register'!$F$5:$F$400,'Cons Issue Register'!$D$5:$D$400,A6) | F6: =SUMIFS('Adjust Register'!$G$5:$G$400,'Adjust Register'!$D$5:$D$400,A6) | G6: =D6+E6+F6 | H6: =IFERROR(SUMIFS('Cons Receipt Register'!$F$5:$F$400,'Cons Receipt Register'!$C$5:$C$400,A6)/D6,0) | I6: =ROUND(G6*H6,2) | J6: =INDEX('M_Consumable'!$E$5:$E$50,MATCH(A6,'M_Consumable'!$A$5:$A$50,0)) | K6: =IF(G6<0,"NEGATIVE",IF(G6<=J6,"REORDER","OK"))
A7: WLD-003 | B7: =INDEX('M_Consumable'!$B$5:$B$50,MATCH(A7,'M_Consumable'!$A$5:$A$50,0)) | C7: =INDEX('M_Consumable'!$D$5:$D$50,MATCH(A7,'M_Consumable'!$A$5:$A$50,0)) | D7: =SUMIFS('Cons Receipt Register'!$D$5:$D$400,'Cons Receipt Register'!$C$5:$C$400,A7) | E7: =SUMIFS('Cons Issue Register'!$F$5:$F$400,'Cons Issue Register'!$D$5:$D$400,A7) | F7: =SUMIFS('Adjust Register'!$G$5:$G$400,'Adjust Register'!$D$5:$D$400,A7) | G7: =D7+E7+F7 | H7: =IFERROR(SUMIFS('Cons Receipt Register'!$F$5:$F$400,'Cons Receipt Register'!$C$5:$C$400,A7)/D7,0) | I7: =ROUND(G7*H7,2) | J7: =INDEX('M_Consumable'!$E$5:$E$50,MATCH(A7,'M_Consumable'!$A$5:$A$50,0)) | K7: =IF(G7<0,"NEGATIVE",IF(G7<=J7,"REORDER","OK"))
A8: GAS-001 | B8: =INDEX('M_Consumable'!$B$5:$B$50,MATCH(A8,'M_Consumable'!$A$5:$A$50,0)) | C8: =INDEX('M_Consumable'!$D$5:$D$50,MATCH(A8,'M_Consumable'!$A$5:$A$50,0)) | D8: =SUMIFS('Cons Receipt Register'!$D$5:$D$400,'Cons Receipt Register'!$C$5:$C$400,A8) | E8: =SUMIFS('Cons Issue Register'!$F$5:$F$400,'Cons Issue Register'!$D$5:$D$400,A8) | F8: =SUMIFS('Adjust Register'!$G$5:$G$400,'Adjust Register'!$D$5:$D$400,A8) | G8: =D8+E8+F8 | H8: =IFERROR(SUMIFS('Cons Receipt Register'!$F$5:$F$400,'Cons Receipt Register'!$C$5:$C$400,A8)/D8,0) | I8: =ROUND(G8*H8,2) | J8: =INDEX('M_Consumable'!$E$5:$E$50,MATCH(A8,'M_Consumable'!$A$5:$A$50,0)) | K8: =IF(G8<0,"NEGATIVE",IF(G8<=J8,"REORDER","OK"))

Sheet M_Material
A1: MATERIAL MASTER
A2: One row per material. Live stock is NOT kept here - see Lot Balance.
A4: Material ID | B4: Grade Code | C4: Grade | D4: Thk mm | E4: Std L mm | F4: Std W mm | G4: Std Sheet kg | H4: Min Level kg | I4: Active
A5: GPSP-1.6 | B5: GP | C5: GPSP | D5: 1.6 | E5: 2500 | F5: 1250 | G5: =ROUND(D5*E5*F5*'Settings'!$B$9,3) | H5: 1500 | I5: Yes
A6: GPSP-1.2 | B6: GP | C6: GPSP | D6: 1.2 | E6: 2500 | F6: 1250 | G6: =ROUND(D6*E6*F6*'Settings'!$B$9,3) | H6: 1000 | I6: Yes
A7: CRCA-1.0 | B7: CR | C7: CRCA | D7: 1 | E7: 2500 | F7: 1250 | G7: =ROUND(D7*E7*F7*'Settings'!$B$9,3) | H7: 800 | I7: Yes
A8: HRCA-2.0 | B8: HR | C8: HRCA | D8: 2 | E8: 2500 | F8: 1250 | G8: =ROUND(D8*E8*F8*'Settings'!$B$9,3) | H8: 600 | I8: Yes

Sheet M_Grade
A1: GRADE CODES
A2: Grade code is the front of every Lot ID.
A4: Grade Code | B4: Grade | C4: Description
A5: GP | B5: GPSP | C5: Galvanised plain
A6: CR | B6: CRCA | C6: Cold rolled
A7: HR | B7: HRCA | C7: Hot rolled
A8: AL | B8: ALUMINIUM | C8: Aluminium

Sheet M_Supplier
A1: SUPPLIERS
A2: Supplier ID is the key; names can change without touching history. Email = plain reference text only.
A4: Supplier ID | B4: Supplier Name | C4: Supplies | D4: GSTIN | E4: Pay Days | F4: Tally Ledger | G4: Email (reference) | H4: Active
A5: SUP-0007 | B5: Supplier A (masked) | C5: RM | D5: 24XXXXX0000X1Z0 | E5: 30 | F5: SUPPLIER A PVT LTD | H5: Yes
A6: SUP-0012 | B6: Supplier B (masked) | C6: RM | D6: 24XXXXX0000X1Z1 | E6: 45 | F6: SUPPLIER B | H6: Yes
A7: SUP-0020 | B7: Supplier C (masked) | C7: CONS | D7: 24XXXXX0000X1Z2 | E7: 30 | F7: SUPPLIER C | H7: Yes

Sheet M_Consumable
A1: CONSUMABLE ITEMS
A2: Identity, unit, category, minimum level. Stock is in Consumable Balance.
A4: Item ID | B4: Item Name | C4: Category | D4: Unit | E4: Min Level | F4: Active
A5: ABR-001 | B5: Flap disc 4 inch | C5: ABRASIVE | D5: NOS | E5: 100 | F5: Yes
A6: ABR-004 | B6: Cutting disc 7 inch | C6: ABRASIVE | D6: NOS | E6: 40 | F6: Yes
A7: WLD-003 | B7: Welding wire 1.2 mm | C7: WELDING | D7: KGS | E7: 50 | F7: Yes
A8: GAS-001 | B8: CO2 gas | C8: GAS | D8: KGS | E8: 200 | F8: Yes

Sheet M_Reason
A1: REASON CODES
A2: Codes, not free text. No count-difference reasons exist.
A4: Code | B4: Reason | C4: Used For
A5: RATE-MKT | B5: Market price moved | C5: GRN rate
A6: OVR-QLT | B6: Lot override - quality / size need | C6: Lot override
A7: ADJ-WGT | B7: Weighing error | C7: Adjustment
A8: ADJ-ENT | B8: Entry error (quote posted ID) | C8: Adjustment
A9: ADJ-DMG | B9: Damage write-off | C9: Adjustment
A10: ADJ-SCN | B10: Supplier credit note | C10: Adjustment
A11: COR-ENT | B11: Correction of a wrong entry | C11: Reversal

Sheet M_WhereUsed
A1: WHERE USED (cost centres)
A2: Consumable destinations.
A4: Where Used | B4: Type
A5: MC-01 SLTL Laser | B5: Machine
A6: MC-05 Amada Bending | B6: Machine
A7: Fabrication Bay | B7: Department
A8: Maintenance | B8: Department

Sheet X_Product
A1: X_PRODUCT - imported from Production (values)
A2: Refreshed by Power Query. Do not type here.
A4: Product ID | B4: Product Name | C4: Customer ID | D4: Active | E4: Run ID
A5: PRD-A12 | B5: Model A12 ODU | C5: CUS-01 | D5: Yes | E5: RUN-270415-0830
A6: PRD-B07 | B6: Model B07 IDU | C6: CUS-01 | D6: Yes | E6: RUN-270415-0830
A7: PRD-C03 | B7: Model C03 frame | C7: CUS-02 | D7: Yes | E7: RUN-270415-0830

Sheet X_Machine
A1: X_MACHINE - imported from Production (values)
A2: Refreshed by Power Query.
A4: Machine ID | B4: Machine | C4: Process | D4: Active
A5: MC-01 | B5: SLTL Laser | C5: CUTTING | D5: Yes
A6: MC-02 | B6: Amada Punching | C6: CUTTING | D6: Yes
A7: MC-03 | B7: Divine Laser | C7: CUTTING | D7: Yes
A8: MC-05 | B8: Amada Bending | C8: BENDING | D8: Yes
A9: MC-07 | B9: Fabrication Bay | C9: FABRICATION | D9: Yes

Sheet X_People
A1: X_PEOPLE - imported from Production (values)
A2: Refreshed by Power Query.
A4: Person ID | B4: Name (masked) | C4: Role | D4: Active
A5: PER-003 | B5: Person 03 | C5: Operator | D5: Yes
A6: PER-007 | B6: Person 07 | C6: Operator | D6: Yes
A7: PER-011 | B7: Person 11 | C7: Operator | D7: Yes
A8: PER-015 | B8: Person 15 | C8: Stores | D8: Yes
A9: PER-018 | B9: Person 18 | C9: QC / approver | D9: Yes

Sheet Posting Log
A1: POSTING LOG
A2: One line per posting: what was posted and the pad control total, so pad = register.
A4: Posted At | B4: Register | C4: Rows Posted | D4: Pad Total kg / Qty | E4: Register Total After | F4: Posted By | G4: Method
A5: 46490.717 | B5: RM Move Register | C5: 2 | D5: 233.3 | E5: 1124.3 | F5: PER-015 | G5: Macro
A6: 46491.501 | B6: Adjust Register | C6: 1 | D6: 4.2 | E6: 4.2 | F6: PER-015 | G6: Manual

Sheet Control Totals
A1: CONTROL TOTALS - read by MIS after refresh
A2: Rows and totals per register; MIS compares its extracts with these.
A4: Register | B4: Rows | C4: Total kg / Qty | D4: Total Value Rs
A5: GRN Register | B5: =COUNTA('GRN Register'!$A$5:$A$400) | C5: =SUM('GRN Register'!$N$5:$N$400) | D5: =SUM('GRN Register'!$T$5:$T$400)
A6: RM Move Register | B6: =COUNTA('RM Move Register'!$A$5:$A$400) | C6: =SUM('RM Move Register'!$J$5:$J$400) | D6: =SUM('RM Move Register'!$M$5:$M$400)
A7: Cons Issue Register | B7: =COUNTA('Cons Issue Register'!$A$5:$A$400) | C7: =SUM('Cons Issue Register'!$F$5:$F$400) | D7: =SUM('Cons Issue Register'!$H$5:$H$400)
A8: Adjust Register | B8: =COUNTA('Adjust Register'!$A$5:$A$400) | C8: =SUM('Adjust Register'!$G$5:$G$400) | D8: =SUM('Adjust Register'!$I$5:$I$400)

Sheet Settings
A1: SETTINGS
A2: The only place parameters are set. Typed values - no TODAY(), no CELL(). Every change goes to the Change Log.
A4: Setting | B4: Value | C4: Note
A5: FY | B5: 2027-28 | C5: Financial year of this file
A6: FYCode | B6: 2728 | C6: Used inside IDs
A7: AsOnDate | B7: 46492 | C7: Typed by the owner each morning
A8: LockDate | B8: 46477 | C8: Entries dated on/before this are rejected
A9: Density | B9: 7.85e-06 | C9: kg per cubic mm (steel)
A10: TolTheo | B10: 0.03 | C10: Theoretical-weight warning
A11: TolRate | B11: 0.02 | C11: Bill vs PO rate warning
A12: POPrefix | B12: PO/27-28/ | C12: PO number prefix
A13: AdjValueLimit | B13: 25000 | C13: Adjustments above this need MD approval
A14: DataFolder | B14: D:\ISKO ERP\FY2027-28\ | C14: Where all four books live

Sheet Lists
A1: LISTS - dropdown sources
A2: Visible; built from masters - no spill formulas.
A4: Movement | B4: Form | C4: QC Status | D4: Excess Decision | E4: Stock Type | F4: Direction
A5: ISSUE | B5: SHEET | C5: ACCEPTED | D5: ACCEPT EXCESS | E5: RM-LOT | F5: INCREASE
A6: RETURN-USABLE | B6: OFFCUT | C6: ACCEPTED WITH REJECTION | D6: RETURN EXCESS | E6: CONSUMABLE | F6: DECREASE
A7: RETURN-OFFCUT | B7: COIL | C7: HOLD
A8: RETURN-DAMAGED | B8: STRIP | C8: REJECTED
A9: STORES-SCRAP
A10: RETURN-TO-SUPPLIER
