Workbook

Sheet README
A1: 3 ISKO DISPATCH & CHALLAN FY2027-28 - requirements, job work, coaters, finished goods, delivery
A2: PROTOTYPE - sample / masked data - layout of the target design, not the live ERP
A4: Daily routine
A5: Start of shift | B5: Refresh All: X_ProdOutput, X_Product. Check Open JWC Balance and FG Balance status.
A6: Job work | B6: JWC Entry: header + lines; post. Coater returns on Coater Move Entry.
A7: Dispatch | B7: DC Entry: header + lines; a line can never exceed FG available (factory) or JWC pending (coater).
A8: Note | B8: Statutory challan documents are produced outside this book (Decision D-03). No print or mail here.
A11: Cell colours
A12: Cream | B12: you type or pick here
A13: Mint | B13: calculated / snapshot - posted as value
A14: Light grey | B14: lookup shown for information
A15: Coral | B15: hard stop - row cannot be posted
A16: Amber | B16: warning - post only with an authorised reason
A17: Teal | B17: totals
A18: Blue | B18: column headers

Sheet JWC Entry
A1: JOB WORK CHALLAN PAD - header + lines
A2: Pick batch and part; qty cannot exceed what production has available to send. Rate comes from Coater Rate on the JWC date.
A3: JWC No | B3: ="JWC/27-28/"&TEXT(COUNTA('JWC Header Register'!$A$5:$A$400)+1,"0000") | C3: Vendor | D3: VEN-001 | E3: Date | F3: 46492 | G3: Vehicle | H3: GJ06-XX-0003 | I3: Purpose | J3: FOR POWDER COATING
A4: e-Way Bill | B4: [number] | C4: Shade | D4: RAL 7035
A6: Line | B6: JWC Line ID | C6: Batch ID | D6: Part ID | E6: Avail to Send | F6: Qty NOS | G6: Wt kg | H6: Sq ft | I6: Basis | J6: PC Rate | K6: PC Cost Rs | L6: Ready / issues
A7: 1 | B7: =IF(C7="","",$B$3&"-"&TEXT(A7,"00")) | C7: ISS-2728-000001 | D7: A12-BP-01 | E7: =IF(C7="","",SUMIFS('X_ProdOutput'!$E$5:$E$50,'X_ProdOutput'!$A$5:$A$50,C7,'X_ProdOutput'!$B$5:$B$50,D7)-SUMIFS(F$6:F6,C$6:C6,C7,D$6:D6,D7)) | F7: 8 | G7: =IF(F7="","",ROUND(F7*INDEX('X_Product'!$C$5:$C$50,MATCH(D7,'X_Product'!$A$5:$A$50,0)),3)) | H7: =IF(F7="","",ROUND(F7*INDEX('X_Product'!$D$5:$D$50,MATCH(D7,'X_Product'!$A$5:$A$50,0)),1)) | I7: =IF(C7="","",INDEX('Coater Rate'!$B$5:$B$50,MATCH($D$3,'Coater Rate'!$A$5:$A$50,0))) | J7: =IF(C7="","",INDEX('Coater Rate'!$C$5:$C$50,MATCH($D$3,'Coater Rate'!$A$5:$A$50,0))) | K7: =IF(C7="","",ROUND(IF(I7="KG",G7,H7)*J7,2)) | L7: =IF(C7="","",IF(F7>E7,"MORE THAN AVAILABLE TO SEND: max "&E7,"READY"))
A8: 2 | B8: =IF(C8="","",$B$3&"-"&TEXT(A8,"00")) | C8: ISS-2728-000002 | D8: B07-CB-02 | E8: =IF(C8="","",SUMIFS('X_ProdOutput'!$E$5:$E$50,'X_ProdOutput'!$A$5:$A$50,C8,'X_ProdOutput'!$B$5:$B$50,D8)-SUMIFS(F$6:F7,C$6:C7,C8,D$6:D7,D8)) | F8: 150 | G8: =IF(F8="","",ROUND(F8*INDEX('X_Product'!$C$5:$C$50,MATCH(D8,'X_Product'!$A$5:$A$50,0)),3)) | H8: =IF(F8="","",ROUND(F8*INDEX('X_Product'!$D$5:$D$50,MATCH(D8,'X_Product'!$A$5:$A$50,0)),1)) | I8: =IF(C8="","",INDEX('Coater Rate'!$B$5:$B$50,MATCH($D$3,'Coater Rate'!$A$5:$A$50,0))) | J8: =IF(C8="","",INDEX('Coater Rate'!$C$5:$C$50,MATCH($D$3,'Coater Rate'!$A$5:$A$50,0))) | K8: =IF(C8="","",ROUND(IF(I8="KG",G8,H8)*J8,2)) | L8: =IF(C8="","",IF(F8>E8,"MORE THAN AVAILABLE TO SEND: max "&E8,"READY"))
A9: 3 | B9: =IF(C9="","",$B$3&"-"&TEXT(A9,"00")) | C9: ISS-2728-000002 | D9: B07-CB-02 | E9: =IF(C9="","",SUMIFS('X_ProdOutput'!$E$5:$E$50,'X_ProdOutput'!$A$5:$A$50,C9,'X_ProdOutput'!$B$5:$B$50,D9)-SUMIFS(F$6:F8,C$6:C8,C9,D$6:D8,D9)) | F9: 40 | G9: =IF(F9="","",ROUND(F9*INDEX('X_Product'!$C$5:$C$50,MATCH(D9,'X_Product'!$A$5:$A$50,0)),3)) | H9: =IF(F9="","",ROUND(F9*INDEX('X_Product'!$D$5:$D$50,MATCH(D9,'X_Product'!$A$5:$A$50,0)),1)) | I9: =IF(C9="","",INDEX('Coater Rate'!$B$5:$B$50,MATCH($D$3,'Coater Rate'!$A$5:$A$50,0))) | J9: =IF(C9="","",INDEX('Coater Rate'!$C$5:$C$50,MATCH($D$3,'Coater Rate'!$A$5:$A$50,0))) | K9: =IF(C9="","",ROUND(IF(I9="KG",G9,H9)*J9,2)) | L9: =IF(C9="","",IF(F9>E9,"MORE THAN AVAILABLE TO SEND: max "&E9,"READY"))

Sheet Coater Move Entry
A1: COATER RETURN / DEFECT PAD
A2: Quote the JWC line. Returns above pending are blocked; defects need a decision.
A4: Coater Move ID | B4: Move Date | C4: Move Type | D4: JWC Line ID | E4: Pending | F4: Qty NOS | G4: Whose Fault | H4: Decision | I4: Coater Challan | J4: Ready / issues
A5: =IF(C5="","","CRT-2728-"&TEXT(COUNTA('Coater Move Register'!$A$5:$A$400)+ROW()-4,"00000")) | B5: 46492 | C5: BACK-OK | D5: JWC/27-28/0001-01 | E5: =IF(D5="","",IFERROR(INDEX('Open JWC Balance'!$I$5:$I$100,MATCH(D5,'Open JWC Balance'!$A$5:$A$100,0)),0)-SUMIFS(F$4:F4,D$4:D4,D5)) | F5: 6 | I5: UMB/C-890 | J5: =IF(C5="","",IF(F5>E5,"MORE THAN PENDING: max "&E5,IF(AND(C5="DEFECT-BACK",H5=""),"DECISION REQUIRED","READY")))
A6: =IF(C6="","","CRT-2728-"&TEXT(COUNTA('Coater Move Register'!$A$5:$A$400)+ROW()-4,"00000")) | B6: 46492 | C6: BACK-OK | D6: JWC/27-28/0002-01 | E6: =IF(D6="","",IFERROR(INDEX('Open JWC Balance'!$I$5:$I$100,MATCH(D6,'Open JWC Balance'!$A$5:$A$100,0)),0)-SUMIFS(F$4:F5,D$4:D5,D6)) | F6: 50 | I6: C2/551 | J6: =IF(C6="","",IF(F6>E6,"MORE THAN PENDING: max "&E6,IF(AND(C6="DEFECT-BACK",H6=""),"DECISION REQUIRED","READY")))
A7: =IF(C7="","","CRT-2728-"&TEXT(COUNTA('Coater Move Register'!$A$5:$A$400)+ROW()-4,"00000")) | B7: 46492 | C7: DEFECT-BACK | D7: JWC/27-28/0001-01 | E7: =IF(D7="","",IFERROR(INDEX('Open JWC Balance'!$I$5:$I$100,MATCH(D7,'Open JWC Balance'!$A$5:$A$100,0)),0)-SUMIFS(F$4:F6,D$4:D6,D7)) | F7: 1 | G7: COATER | I7: UMB/C-890 | J7: =IF(C7="","",IF(F7>E7,"MORE THAN PENDING: max "&E7,IF(AND(C7="DEFECT-BACK",H7=""),"DECISION REQUIRED","READY")))

Sheet DC Entry
A1: DELIVERY CHALLAN PAD - header + lines
A2: From FACTORY a line cannot exceed FG available; from a coater it must quote the JWC line and cannot exceed pending. UOM and rate from Customer Price & UOM.
A3: Challan No | B3: ="DC/27-28/"&TEXT(COUNTA('DC Header Register'!$A$5:$A$400)+1,"0000") | C3: Customer | D3: CUS-01 | E3: Date | F3: 46492 | G3: From | H3: FACTORY | I3: Vehicle | J3: GJ06-XX-0103
A4: LR No | B4: [ref] | C4: Invoice | D4: [ref] | E4: e-Way Bill | F4: [number] | G4: Driver | H4: [name]
A6: Line | B6: DC Line ID | C6: Req ID | D6: Part ID | E6: Qty | F6: Available | G6: UOM | H6: Wt / Unit | I6: Wt kg | J6: Challan Qty | K6: Rate Rs/kg | L6: Value Rs | M6: Ready / issues
A7: 1 | B7: =IF(D7="","",$B$3&"-"&TEXT(A7,"00")) | C7: REQ-2728-00002 | D7: A12-BP-01 | E7: 4 | F7: =IF(D7="","",IFERROR(INDEX('FG Balance'!$F$5:$F$100,MATCH(D7,'FG Balance'!$A$5:$A$100,0)),0)-SUMIFS(E$6:E6,D$6:D6,D7)) | G7: {=IF(D7="","",IFERROR(INDEX('Customer Price & UOM'!$D$5:$D$50,MATCH(1,('Customer Price & UOM'!$A$5:$A$50=$D$3)*('Customer Price & UOM'!$C$5:$C$50=D7),0)),""))} | H7: {=IF(D7="","",IFERROR(INDEX('Customer Price & UOM'!$E$5:$E$50,MATCH(1,('Customer Price & UOM'!$A$5:$A$50=$D$3)*('Customer Price & UOM'!$C$5:$C$50=D7),0)),0))} | I7: =IF(E7="","",ROUND(E7*H7,3)) | J7: =IF(E7="","",IF(G7="KG",I7,IF(G7="TON",ROUND(I7/1000,3),E7))) | K7: {=IF(D7="","",IFERROR(INDEX('Customer Price & UOM'!$F$5:$F$50,MATCH(1,('Customer Price & UOM'!$A$5:$A$50=$D$3)*('Customer Price & UOM'!$C$5:$C$50=D7),0)),0))} | L7: =IF(E7="","",ROUND(I7*K7,2)) | M7: =IF(D7="","",IF(G7="","NO UOM / PRICE FOR CUSTOMER + PART",IF(E7>F7,"ABOVE FG AVAILABLE: max "&F7,IF(C7="","WARN: no Req ID","READY"))))
A8: 2 | B8: =IF(D8="","",$B$3&"-"&TEXT(A8,"00")) | C8: REQ-2728-00002 | D8: A12-BP-01 | E8: 10 | F8: =IF(D8="","",IFERROR(INDEX('FG Balance'!$F$5:$F$100,MATCH(D8,'FG Balance'!$A$5:$A$100,0)),0)-SUMIFS(E$6:E7,D$6:D7,D8)) | G8: {=IF(D8="","",IFERROR(INDEX('Customer Price & UOM'!$D$5:$D$50,MATCH(1,('Customer Price & UOM'!$A$5:$A$50=$D$3)*('Customer Price & UOM'!$C$5:$C$50=D8),0)),""))} | H8: {=IF(D8="","",IFERROR(INDEX('Customer Price & UOM'!$E$5:$E$50,MATCH(1,('Customer Price & UOM'!$A$5:$A$50=$D$3)*('Customer Price & UOM'!$C$5:$C$50=D8),0)),0))} | I8: =IF(E8="","",ROUND(E8*H8,3)) | J8: =IF(E8="","",IF(G8="KG",I8,IF(G8="TON",ROUND(I8/1000,3),E8))) | K8: {=IF(D8="","",IFERROR(INDEX('Customer Price & UOM'!$F$5:$F$50,MATCH(1,('Customer Price & UOM'!$A$5:$A$50=$D$3)*('Customer Price & UOM'!$C$5:$C$50=D8),0)),0))} | L8: =IF(E8="","",ROUND(I8*K8,2)) | M8: =IF(D8="","",IF(G8="","NO UOM / PRICE FOR CUSTOMER + PART",IF(E8>F8,"ABOVE FG AVAILABLE: max "&F8,IF(C8="","WARN: no Req ID","READY"))))
A9: 3 | B9: =IF(D9="","",$B$3&"-"&TEXT(A9,"00")) | D9: C03-FR-01 | E9: 5 | F9: =IF(D9="","",IFERROR(INDEX('FG Balance'!$F$5:$F$100,MATCH(D9,'FG Balance'!$A$5:$A$100,0)),0)-SUMIFS(E$6:E8,D$6:D8,D9)) | G9: {=IF(D9="","",IFERROR(INDEX('Customer Price & UOM'!$D$5:$D$50,MATCH(1,('Customer Price & UOM'!$A$5:$A$50=$D$3)*('Customer Price & UOM'!$C$5:$C$50=D9),0)),""))} | H9: {=IF(D9="","",IFERROR(INDEX('Customer Price & UOM'!$E$5:$E$50,MATCH(1,('Customer Price & UOM'!$A$5:$A$50=$D$3)*('Customer Price & UOM'!$C$5:$C$50=D9),0)),0))} | I9: =IF(E9="","",ROUND(E9*H9,3)) | J9: =IF(E9="","",IF(G9="KG",I9,IF(G9="TON",ROUND(I9/1000,3),E9))) | K9: {=IF(D9="","",IFERROR(INDEX('Customer Price & UOM'!$F$5:$F$50,MATCH(1,('Customer Price & UOM'!$A$5:$A$50=$D$3)*('Customer Price & UOM'!$C$5:$C$50=D9),0)),0))} | L9: =IF(E9="","",ROUND(I9*K9,2)) | M9: =IF(D9="","",IF(G9="","NO UOM / PRICE FOR CUSTOMER + PART",IF(E9>F9,"ABOVE FG AVAILABLE: max "&F9,IF(C9="","WARN: no Req ID","READY"))))

Sheet Requirement Register
A1: CUSTOMER REQUIREMENT REGISTER - versioned
A2: A revision is a new row quoting the row it revises; the old one becomes SUPERSEDED.
A4: Req ID | B4: Version | C4: Revises | D4: Entry Date | E4: Customer ID | F4: Product ID | G4: Required Qty | H4: Required Date | I4: Priority | J4: Status | K4: Dispatched Qty | L4: Pending Qty
A5: REQ-2728-00001 | B5: 1 | D5: 46479 | E5: CUS-01 | F5: PRD-A12 | G5: 200 | H5: 46507 | I5: 1 | J5: SUPERSEDED | K5: =SUMIFS('DC Line Register'!$J$5:$J$400,'DC Line Register'!$D$5:$D$400,A5) | L5: =IF(J5="SUPERSEDED",0,MAX(0,G5-K5))
A6: REQ-2728-00002 | B6: 2 | C6: REQ-2728-00001 | D6: 46486 | E6: CUS-01 | F6: PRD-A12 | G6: 240 | H6: 46507 | I6: 1 | J6: OPEN | K6: =SUMIFS('DC Line Register'!$J$5:$J$400,'DC Line Register'!$D$5:$D$400,A6) | L6: =IF(J6="SUPERSEDED",0,MAX(0,G6-K6))
A7: REQ-2728-00003 | B7: 1 | D7: 46482 | E7: CUS-02 | F7: PRD-C03 | G7: 30 | H7: 46497 | I7: 2 | J7: OPEN | K7: =SUMIFS('DC Line Register'!$J$5:$J$400,'DC Line Register'!$D$5:$D$400,A7) | L7: =IF(J7="SUPERSEDED",0,MAX(0,G7-K7))

Sheet JWC Header Register
A1: JWC HEADER REGISTER - values only
A2: JWC numbers are sequential per FY, no gaps; cancellation is a status line.
A4: JWC No | B4: JWC Date | C4: Vendor ID | D4: Vendor Name | E4: Vehicle No | F4: e-Way Bill | G4: Purpose | H4: Status | I4: Posted At
A5: JWC/27-28/0001 | B5: 46490 | C5: VEN-001 | D5: Coater 1 (masked) | E5: GJ06-XX-0001 | F5: [number] | G5: FOR POWDER COATING | H5: OPEN | I5: 46490.667
A6: JWC/27-28/0002 | B6: 46491 | C6: VEN-002 | D6: Coater 2 (masked) | E6: GJ06-XX-0002 | F6: [number] | G6: FOR POWDER COATING | H6: OPEN | I6: 46491.625

Sheet JWC Line Register
A1: JWC LINE REGISTER - values only
A2: Rate, basis, sq ft and lot frozen at posting. Returns and pending are in Open JWC Balance.
A4: JWC Line ID | B4: JWC No | C4: JWC Date | D4: Vendor ID | E4: Batch ID | F4: Part ID | G4: Qty NOS | H4: Wt kg | I4: Sq ft | J4: Basis | K4: PC Rate | L4: PC Cost Rs | M4: Posted At
A5: JWC/27-28/0001-01 | B5: JWC/27-28/0001 | C5: 46490 | D5: VEN-001 | E5: ISS-2728-000001 | F5: A12-BP-01 | G5: 40 | H5: 248.6 | I5: 166 | J5: SQFT | K5: 13.5 | L5: 2241 | M5: 46490.667
A6: JWC/27-28/0002-01 | B6: JWC/27-28/0002 | C6: 46491 | D6: VEN-002 | E6: ISS-2728-000002 | F6: B07-CB-02 | G6: 100 | H6: 115 | I6: 90 | J6: KG | K6: 27 | L6: 3105 | M6: 46491.625

Sheet Coater Move Register
A1: COATER MOVEMENT REGISTER - opening, returns, defects
A2: BACK-OK puts goods into FG; DEFECT-BACK needs a decision; OPENING only at cut-over.
A4: Coater Move ID | B4: Move Date | C4: Move Type | D4: Vendor ID | E4: JWC Line ID | F4: Part ID | G4: Qty NOS | H4: Wt kg | I4: Whose Fault | J4: Decision | K4: Debit Rs | L4: Coater Challan | M4: Posted At
A5: CRT-2728-00001 | B5: 46478 | C5: OPENING | D5: VEN-001 | F5: A12-BP-01 | G5: 20 | H5: 124.3 | L5: Statement 31-Mar | M5: 46478.375
A6: CRT-2728-00002 | B6: 46492 | C6: BACK-OK | D6: VEN-001 | E6: JWC/27-28/0001-01 | F6: A12-BP-01 | G6: 30 | H6: 186.45 | L6: UMB/C-881 | M6: 46492.458
A7: CRT-2728-00003 | B7: 46492 | C7: DEFECT-BACK | D7: VEN-001 | E7: JWC/27-28/0001-01 | F7: A12-BP-01 | G7: 2 | H7: 12.43 | I7: COATER | J7: RE-SEND | L7: UMB/C-881 | M7: 46492.458

Sheet DC Header Register
A1: DC HEADER REGISTER - values only
A2: DC numbers sequential per FY, no gaps.
A4: Challan No | B4: DC Date | C4: Customer ID | D4: Dispatch From | E4: Vehicle No | F4: LR No | G4: Invoice No | H4: e-Way Bill | I4: Status | J4: Posted At
A5: DC/27-28/0001 | B5: 46491 | C5: CUS-01 | D5: FACTORY | E5: GJ06-XX-0101 | F5: [ref] | G5: [ref] | H5: [number] | I5: DISPATCHED | J5: 46491.708
A6: DC/27-28/0002 | B6: 46492 | C6: CUS-01 | D6: VEN-002 | E6: GJ06-XX-0102 | F6: [ref] | G6: [ref] | H6: [number] | I6: DISPATCHED | J6: 46492.5

Sheet DC Line Register
A1: DC LINE REGISTER - values only
A2: UOM, weight per unit and rate frozen at posting.
A4: DC Line ID | B4: Challan No | C4: DC Date | D4: Req ID | E4: Dispatch From | F4: JWC Line ID | G4: Part ID | H4: Batch ID | I4: Type | J4: Qty | K4: UOM | L4: Wt kg | M4: Challan Qty | N4: Rate Rs/kg | O4: Value Rs
A5: DC/27-28/0001-01 | B5: DC/27-28/0001 | C5: 46491 | D5: REQ-2728-00002 | E5: FACTORY | G5: A12-BP-01 | H5: ISS-2728-000001 | I5: SALE | J5: 25 | K5: QTY | L5: 155.375 | M5: 25 | N5: 173.24 | O5: 26917.17
A6: DC/27-28/0002-01 | B6: DC/27-28/0002 | C6: 46492 | E6: VEN-002 | F6: JWC/27-28/0002-01 | G6: B07-CB-02 | H6: ISS-2728-000002 | I6: SALE | J6: 60 | K6: QTY | L6: 69 | M6: 60 | N6: 165.1 | O6: 11391.9

Sheet Open JWC Balance
A1: OPEN JWC / AT-COATER BALANCE (calculated)
A2: Pending = sent - back OK - defect back - direct dispatch. Ageing from JWC date.
A3: Coater opening (cut-over) qty: | B3: =SUMIFS('Coater Move Register'!$G$5:$G$400,'Coater Move Register'!$C$5:$C$400,"OPENING")
A4: JWC Line ID | B4: Vendor ID | C4: JWC Date | D4: Part ID | E4: Sent | F4: Back OK | G4: Defect Back | H4: Direct DC | I4: Pending Qty | J4: Pending kg | K4: Days | L4: Status
A5: JWC/27-28/0001-01 | B5: =INDEX('JWC Line Register'!$D$5:$D$400,MATCH(A5,'JWC Line Register'!$A$5:$A$400,0)) | C5: =INDEX('JWC Line Register'!$C$5:$C$400,MATCH(A5,'JWC Line Register'!$A$5:$A$400,0)) | D5: =INDEX('JWC Line Register'!$F$5:$F$400,MATCH(A5,'JWC Line Register'!$A$5:$A$400,0)) | E5: =INDEX('JWC Line Register'!$G$5:$G$400,MATCH(A5,'JWC Line Register'!$A$5:$A$400,0)) | F5: =SUMIFS('Coater Move Register'!$G$5:$G$400,'Coater Move Register'!$E$5:$E$400,A5,'Coater Move Register'!$C$5:$C$400,"BACK-OK") | G5: =SUMIFS('Coater Move Register'!$G$5:$G$400,'Coater Move Register'!$E$5:$E$400,A5,'Coater Move Register'!$C$5:$C$400,"DEFECT-BACK") | H5: =SUMIFS('DC Line Register'!$J$5:$J$400,'DC Line Register'!$F$5:$F$400,A5) | I5: =E5-F5-G5-H5 | J5: =ROUND(I5*INDEX('JWC Line Register'!$H$5:$H$400,MATCH(A5,'JWC Line Register'!$A$5:$A$400,0))/E5,3) | K5: ='Settings'!$B$7-C5 | L5: =IF(I5<0,"BREACH - more back than sent",IF(I5=0,"CLOSED",IF(K5>'Settings'!$B$11,"WARN: over age",IF(F5+G5+H5>0,"PART RETURNED","PENDING"))))
A6: JWC/27-28/0002-01 | B6: =INDEX('JWC Line Register'!$D$5:$D$400,MATCH(A6,'JWC Line Register'!$A$5:$A$400,0)) | C6: =INDEX('JWC Line Register'!$C$5:$C$400,MATCH(A6,'JWC Line Register'!$A$5:$A$400,0)) | D6: =INDEX('JWC Line Register'!$F$5:$F$400,MATCH(A6,'JWC Line Register'!$A$5:$A$400,0)) | E6: =INDEX('JWC Line Register'!$G$5:$G$400,MATCH(A6,'JWC Line Register'!$A$5:$A$400,0)) | F6: =SUMIFS('Coater Move Register'!$G$5:$G$400,'Coater Move Register'!$E$5:$E$400,A6,'Coater Move Register'!$C$5:$C$400,"BACK-OK") | G6: =SUMIFS('Coater Move Register'!$G$5:$G$400,'Coater Move Register'!$E$5:$E$400,A6,'Coater Move Register'!$C$5:$C$400,"DEFECT-BACK") | H6: =SUMIFS('DC Line Register'!$J$5:$J$400,'DC Line Register'!$F$5:$F$400,A6) | I6: =E6-F6-G6-H6 | J6: =ROUND(I6*INDEX('JWC Line Register'!$H$5:$H$400,MATCH(A6,'JWC Line Register'!$A$5:$A$400,0))/E6,3) | K6: ='Settings'!$B$7-C6 | L6: =IF(I6<0,"BREACH - more back than sent",IF(I6=0,"CLOSED",IF(K6>'Settings'!$B$11,"WARN: over age",IF(F6+G6+H6>0,"PART RETURNED","PENDING"))))

Sheet FG Balance
A1: FINISHED-GOODS BALANCE - transaction-calculated (no counts)
A2: FG = opening + coater BACK-OK + uncoated final-stage completion - dispatch from factory +/- authorised adjustment.
A4: Part ID | B4: FG Opening | C4: In: Back OK | D4: In: Uncoated | E4: Out: DC from Factory | F4: FG Available | G4: Status
A5: A12-BP-01 | B5: 0 | C5: =SUMIFS('Coater Move Register'!$G$5:$G$400,'Coater Move Register'!$F$5:$F$400,A5,'Coater Move Register'!$C$5:$C$400,"BACK-OK") | D5: 0 | E5: =SUMIFS('DC Line Register'!$J$5:$J$400,'DC Line Register'!$G$5:$G$400,A5,'DC Line Register'!$E$5:$E$400,"FACTORY") | F5: =B5+C5+D5-E5 | G5: =IF(F5<0,"BREACH - negative FG","OK")
A6: B07-CB-02 | B6: 0 | C6: =SUMIFS('Coater Move Register'!$G$5:$G$400,'Coater Move Register'!$F$5:$F$400,A6,'Coater Move Register'!$C$5:$C$400,"BACK-OK") | D6: 0 | E6: =SUMIFS('DC Line Register'!$J$5:$J$400,'DC Line Register'!$G$5:$G$400,A6,'DC Line Register'!$E$5:$E$400,"FACTORY") | F6: =B6+C6+D6-E6 | G6: =IF(F6<0,"BREACH - negative FG","OK")
A7: C03-FR-01 | B7: 0 | C7: =SUMIFS('Coater Move Register'!$G$5:$G$400,'Coater Move Register'!$F$5:$F$400,A7,'Coater Move Register'!$C$5:$C$400,"BACK-OK") | D7: 0 | E7: =SUMIFS('DC Line Register'!$J$5:$J$400,'DC Line Register'!$G$5:$G$400,A7,'DC Line Register'!$E$5:$E$400,"FACTORY") | F7: =B7+C7+D7-E7 | G7: =IF(F7<0,"BREACH - negative FG","OK")

Sheet M_Customer
A1: CUSTOMERS
A2: Dispatch UOM is mandatory. Email = plain reference only.
A4: Customer ID | B4: Customer Name | C4: State Code | D4: GSTIN | E4: Tally Ledger | F4: Dispatch UOM | G4: Active
A5: CUS-01 | B5: Customer 1 (masked) | C5: 27 | D5: 27XXXXX0000X1Z5 | E5: CUSTOMER 1 LTD | F5: QTY | G5: Yes
A6: CUS-02 | B6: Customer 2 (masked) | C6: 24 | D6: 24XXXXX0000X1Z8 | E6: CUSTOMER 2 | F6: KG | G6: Yes

Sheet Customer Price & UOM
A1: CUSTOMER PRICE & UOM - effective-dated
A2: A new rate is a new row with a new Effective From; posted DC lines keep their rate.
A4: Customer ID | B4: Product ID | C4: Part ID | D4: UOM | E4: Wt per Unit kg | F4: Rate Rs/kg | G4: Effective From
A5: CUS-01 | B5: PRD-A12 | C5: A12-BP-01 | D5: QTY | E5: 6.215 | F5: 173.24 | G5: 46478
A6: CUS-01 | B6: PRD-B07 | C6: B07-CB-02 | D6: QTY | E6: 1.15 | F6: 165.1 | G6: 46478
A7: CUS-02 | B7: PRD-C03 | C7: C03-FR-01 | D7: KG | E7: 12.4 | F7: 92.5 | G7: 46478

Sheet M_Vendor
A1: VENDORS / COATERS
A2: Identity only; rates are in Coater Rate.
A4: Vendor ID | B4: Vendor Name | C4: GSTIN | D4: Status
A5: VEN-001 | B5: Coater 1 (masked) | C5: 24XXXXX0000X1Z3 | D5: Active
A6: VEN-002 | B6: Coater 2 (masked) | C6: 24XXXXX0000X1Z4 | D6: Active

Sheet Coater Rate
A1: COATER RATE - effective-dated
A2: JWC lines copy the rate in force on the JWC date.
A4: Vendor ID | B4: Basis | C4: Rate Rs | D4: Effective From
A5: VEN-001 | B5: SQFT | C5: 13.5 | D5: 46478
A6: VEN-002 | B6: KG | C6: 27 | D6: 46478

Sheet X_Product
A1: X_PRODUCT / PART - from Production (values)
A2: Power Query extract.
A4: Part ID | B4: Product ID | C4: Wt/pc kg | D4: Sq ft/pc | E4: Coating Route
A5: A12-BP-01 | B5: PRD-A12 | C5: 6.215 | D5: 4.15 | E5: POWDER COAT
A6: A12-SP-04 | B6: PRD-A12 | C6: 2.01 | D6: 1.6 | E6: POWDER COAT
A7: B07-CB-02 | B7: PRD-B07 | C7: 1.15 | D7: 0.9 | E7: POWDER COAT
A8: C03-FR-01 | B8: PRD-C03 | C8: 12.4 | D8: 6.2 | E8: NO COATING

Sheet X_ProdOutput
A1: X_PROD OUTPUT - QC-OK parts available to send (values)
A2: From Production: completed at the last route stage, net of rejections, by batch.
A4: Batch ID | B4: Part ID | C4: QC-OK Qty | D4: Already on JWC | E4: Available to Send | F4: Run ID
A5: ISS-2728-000001 | B5: A12-BP-01 | C5: 49 | D5: =SUMIFS('JWC Line Register'!$G$5:$G$400,'JWC Line Register'!$E$5:$E$400,A5,'JWC Line Register'!$F$5:$F$400,B5) | E5: =C5-D5 | F5: RUN-270415-0800
A6: ISS-2728-000002 | B6: B07-CB-02 | C6: 280 | D6: =SUMIFS('JWC Line Register'!$G$5:$G$400,'JWC Line Register'!$E$5:$E$400,A6,'JWC Line Register'!$F$5:$F$400,B6) | E6: =C6-D6 | F6: RUN-270415-0800

Sheet Control Totals
A1: CONTROL TOTALS - read by MIS
A2: Rows and totals per register.
A4: Register | B4: Rows | C4: Total Qty | D4: Total kg / Rs
A5: JWC Line Register | B5: =COUNTA('JWC Line Register'!$A$5:$A$400) | C5: =SUM('JWC Line Register'!$G$5:$G$400) | D5: =SUM('JWC Line Register'!$H$5:$H$400)
A6: Coater Move Register | B6: =COUNTA('Coater Move Register'!$A$5:$A$400) | C6: =SUM('Coater Move Register'!$G$5:$G$400) | D6: =SUM('Coater Move Register'!$H$5:$H$400)
A7: DC Line Register | B7: =COUNTA('DC Line Register'!$A$5:$A$400) | C7: =SUM('DC Line Register'!$J$5:$J$400) | D7: =SUM('DC Line Register'!$O$5:$O$400)

Sheet Settings
A1: SETTINGS
A2: The only place parameters are set. Typed values - no TODAY(), no CELL(). Every change goes to the Change Log.
A4: Setting | B4: Value | C4: Note
A5: FY | B5: 2027-28
A6: FYCode | B6: 2728
A7: AsOnDate | B7: 46492 | C7: Typed
A8: LockDate | B8: 46477
A9: DCPrefix | B9: DC/27-28/
A10: JWCPrefix | B10: JWC/27-28/
A11: CoaterAge days | B11: 15 | C11: Ageing warning
A12: ProductionFile | B12: 2 ISKO Production FY2027-28.xlsx | C12: Source of X_ProdOutput

Sheet Lists
A1: LISTS - dropdown sources
A2: Visible; built from masters - no spill formulas.
A4: Coater Move Type | B4: Decision | C4: DC Type | D4: UOM
A5: OPENING | B5: REWORK AT COATER | C5: SALE | D5: QTY
A6: BACK-OK | B6: RE-SEND | C6: REPLACEMENT | D6: NOS
A7: DEFECT-BACK | B7: SCRAP | C7: SAMPLE | D7: SET
A8: DEFECT-AT-COATER-SCRAP | B8: DEBIT COATER | D8: KG
D9: TON
